{
"meta":{"test_sets":[],"test_metrics":[],"learn_metrics":[{"best_value":"Min","name":"RMSE"}],"launch_mode":"Train","parameters":"","iteration_count":1000,"learn_sets":["learn"],"name":"experiment"},
"iterations":[
{"learn":[14.59871775],"iteration":0,"passed_time":0.1395541899,"remaining_time":139.4146357},
{"learn":[14.22518863],"iteration":1,"passed_time":0.1410228694,"remaining_time":70.37041184},
{"learn":[13.8866124],"iteration":2,"passed_time":0.1427392256,"remaining_time":47.43700263},
{"learn":[13.52356875],"iteration":3,"passed_time":0.1445730912,"remaining_time":35.99869971},
{"learn":[13.18870211],"iteration":4,"passed_time":0.1479562619,"remaining_time":29.44329612},
{"learn":[12.9124226],"iteration":5,"passed_time":0.1491656414,"remaining_time":24.71177459},
{"learn":[12.60003351],"iteration":6,"passed_time":0.1514142361,"remaining_time":21.47919092},
{"learn":[12.32990573],"iteration":7,"passed_time":0.15285506,"remaining_time":18.95402743},
{"learn":[12.0660619],"iteration":8,"passed_time":0.1548767099,"remaining_time":17.05364661},
{"learn":[11.77309809],"iteration":9,"passed_time":0.1567764777,"remaining_time":15.5208713},
{"learn":[11.49227636],"iteration":10,"passed_time":0.1595762056,"remaining_time":14.34735158},
{"learn":[11.26264833],"iteration":11,"passed_time":0.1610383639,"remaining_time":13.25882529},
{"learn":[11.04260393],"iteration":12,"passed_time":0.1629707255,"remaining_time":12.37323893},
{"learn":[10.79916926],"iteration":13,"passed_time":0.165551751,"remaining_time":11.65957332},
{"learn":[10.5541002],"iteration":14,"passed_time":0.1672012649,"remaining_time":10.97954973},
{"learn":[10.31918115],"iteration":15,"passed_time":0.168240003,"remaining_time":10.34676018},
{"learn":[10.10004441],"iteration":16,"passed_time":0.1694264739,"remaining_time":9.796836694},
{"learn":[9.894556723],"iteration":17,"passed_time":0.1710160576,"remaining_time":9.329876034},
{"learn":[9.690174082],"iteration":18,"passed_time":0.1724986685,"remaining_time":8.906378621},
{"learn":[9.506034866],"iteration":19,"passed_time":0.17383438,"remaining_time":8.517884619},
{"learn":[9.338524633],"iteration":20,"passed_time":0.1749059875,"remaining_time":8.15395056},
{"learn":[9.170203312],"iteration":21,"passed_time":0.1763170539,"remaining_time":7.838094486},
{"learn":[9.010299969],"iteration":22,"passed_time":0.1780292767,"remaining_time":7.562374057},
{"learn":[8.843866678],"iteration":23,"passed_time":0.1796123835,"remaining_time":7.30423693},
{"learn":[8.690548059],"iteration":24,"passed_time":0.1808440168,"remaining_time":7.052916653},
{"learn":[8.555307687],"iteration":25,"passed_time":0.1822565,"remaining_time":6.827608883},
{"learn":[8.413851302],"iteration":26,"passed_time":0.1831083455,"remaining_time":6.59868223},
{"learn":[8.29256019],"iteration":27,"passed_time":0.1846035343,"remaining_time":6.408379833},
{"learn":[8.162193833],"iteration":28,"passed_time":0.1863696122,"remaining_time":6.240168739},
{"learn":[8.040736294],"iteration":29,"passed_time":0.1875529348,"remaining_time":6.064211559},
{"learn":[7.921220278],"iteration":30,"passed_time":0.1886444752,"remaining_time":5.896661176},
{"learn":[7.809589039],"iteration":31,"passed_time":0.1900102051,"remaining_time":5.747808703},
{"learn":[7.699675801],"iteration":32,"passed_time":0.1915758314,"remaining_time":5.613752392},
{"learn":[7.60645267],"iteration":33,"passed_time":0.1937355011,"remaining_time":5.504367473},
{"learn":[7.498880302],"iteration":34,"passed_time":0.1949495471,"remaining_time":5.375037512},
{"learn":[7.401158744],"iteration":35,"passed_time":0.1961875191,"remaining_time":5.25346579},
{"learn":[7.306431077],"iteration":36,"passed_time":0.1972556938,"remaining_time":5.133979275},
{"learn":[7.223863468],"iteration":37,"passed_time":0.1981876459,"remaining_time":5.017276719},
{"learn":[7.143477682],"iteration":38,"passed_time":0.199467544,"remaining_time":4.915084866},
{"learn":[7.062817131],"iteration":39,"passed_time":0.2005268835,"remaining_time":4.812645205},
{"learn":[6.990793435],"iteration":40,"passed_time":0.2019769566,"remaining_time":4.724290278},
{"learn":[6.931862224],"iteration":41,"passed_time":0.2028483007,"remaining_time":4.626873145},
{"learn":[6.858296558],"iteration":42,"passed_time":0.2038410748,"remaining_time":4.536649038},
{"learn":[6.786268161],"iteration":43,"passed_time":0.2049296969,"remaining_time":4.452563413},
{"learn":[6.717118549],"iteration":44,"passed_time":0.2060310799,"remaining_time":4.372437362},
{"learn":[6.652948106],"iteration":45,"passed_time":0.2072218533,"remaining_time":4.297601044},
{"learn":[6.589686076],"iteration":46,"passed_time":0.2088435391,"remaining_time":4.234636017},
{"learn":[6.531283097],"iteration":47,"passed_time":0.2104244756,"remaining_time":4.173418765},
{"learn":[6.471368031],"iteration":48,"passed_time":0.2114565176,"remaining_time":4.103982617},
{"learn":[6.416481395],"iteration":49,"passed_time":0.2124054067,"remaining_time":4.035702728},
{"learn":[6.369870822],"iteration":50,"passed_time":0.2132263645,"remaining_time":3.967682744},
{"learn":[6.325678067],"iteration":51,"passed_time":0.2140612383,"remaining_time":3.902501037},
{"learn":[6.275766122],"iteration":52,"passed_time":0.2150873689,"remaining_time":3.843164875},
{"learn":[6.224773967],"iteration":53,"passed_time":0.2162345999,"remaining_time":3.788109842},
{"learn":[6.182249254],"iteration":54,"passed_time":0.2171156499,"remaining_time":3.73044162},
{"learn":[6.139904173],"iteration":55,"passed_time":0.2178971676,"remaining_time":3.673123683},
{"learn":[6.100525536],"iteration":56,"passed_time":0.2189020643,"remaining_time":3.621485028},
{"learn":[6.062568564],"iteration":57,"passed_time":0.2199072351,"remaining_time":3.571596819},
{"learn":[6.030559288],"iteration":58,"passed_time":0.2212481302,"remaining_time":3.528720178},
{"learn":[5.997931376],"iteration":59,"passed_time":0.2229555037,"remaining_time":3.492969558},
{"learn":[5.964103835],"iteration":60,"passed_time":0.2239563197,"remaining_time":3.447458757},
{"learn":[5.933729724],"iteration":61,"passed_time":0.2249900284,"remaining_time":3.403881397},
{"learn":[5.901932711],"iteration":62,"passed_time":0.2259311085,"remaining_time":3.360276963},
{"learn":[5.873727795],"iteration":63,"passed_time":0.2269004396,"remaining_time":3.318418929},
{"learn":[5.846485734],"iteration":64,"passed_time":0.2280011287,"remaining_time":3.279708544},
{"learn":[5.820630862],"iteration":65,"passed_time":0.2290372531,"remaining_time":3.241224157},
{"learn":[5.793646238],"iteration":66,"passed_time":0.2305317492,"remaining_time":3.210240628},
{"learn":[5.765388646],"iteration":67,"passed_time":0.2315470987,"remaining_time":3.173557294},
{"learn":[5.747073912],"iteration":68,"passed_time":0.2325291608,"remaining_time":3.137458677},
{"learn":[5.722315217],"iteration":69,"passed_time":0.2338370677,"remaining_time":3.10669247},
{"learn":[5.699970599],"iteration":70,"passed_time":0.2345962827,"remaining_time":3.069576712},
{"learn":[5.682732647],"iteration":71,"passed_time":0.2357150078,"remaining_time":3.038104545},
{"learn":[5.663525791],"iteration":72,"passed_time":0.236700083,"remaining_time":3.005766807},
{"learn":[5.642381613],"iteration":73,"passed_time":0.2393756446,"remaining_time":2.995430364},
{"learn":[5.621404779],"iteration":74,"passed_time":0.2403803258,"remaining_time":2.964690685},
{"learn":[5.602460129],"iteration":75,"passed_time":0.2417367971,"remaining_time":2.939010533},
{"learn":[5.587337574],"iteration":76,"passed_time":0.2432263213,"remaining_time":2.915557072},
{"learn":[5.572393026],"iteration":77,"passed_time":0.2443262748,"remaining_time":2.888061864},
{"learn":[5.558425806],"iteration":78,"passed_time":0.2455362147,"remaining_time":2.862517136},
{"learn":[5.541518902],"iteration":79,"passed_time":0.246653043,"remaining_time":2.836509995},
{"learn":[5.526157283],"iteration":80,"passed_time":0.2478552393,"remaining_time":2.812085987},
{"learn":[5.511746977],"iteration":81,"passed_time":0.248686674,"remaining_time":2.784077643},
{"learn":[5.504975022],"iteration":82,"passed_time":0.2490428655,"remaining_time":2.751473586},
{"learn":[5.493980522],"iteration":83,"passed_time":0.2500316003,"remaining_time":2.72653507},
{"learn":[5.480745463],"iteration":84,"passed_time":0.2511158621,"remaining_time":2.703188398},
{"learn":[5.464052013],"iteration":85,"passed_time":0.2521440086,"remaining_time":2.679763068},
{"learn":[5.449143727],"iteration":86,"passed_time":0.2532200361,"remaining_time":2.657355091},
{"learn":[5.438255432],"iteration":87,"passed_time":0.2543669294,"remaining_time":2.63616636},
{"learn":[5.425927931],"iteration":88,"passed_time":0.2552287311,"remaining_time":2.612509821},
{"learn":[5.412331217],"iteration":89,"passed_time":0.2562342289,"remaining_time":2.590812759},
{"learn":[5.400691499],"iteration":90,"passed_time":0.2571897491,"remaining_time":2.56907123},
{"learn":[5.391618744],"iteration":91,"passed_time":0.2580850607,"remaining_time":2.547187338},
{"learn":[5.380766572],"iteration":92,"passed_time":0.2590026043,"remaining_time":2.525971636},
{"learn":[5.372207183],"iteration":93,"passed_time":0.2601675977,"remaining_time":2.507572804},
{"learn":[5.362918837],"iteration":94,"passed_time":0.2614246086,"remaining_time":2.490413377},
{"learn":[5.348292324],"iteration":95,"passed_time":0.2624480653,"remaining_time":2.471385948},
{"learn":[5.339772295],"iteration":96,"passed_time":0.2633905462,"remaining_time":2.45197591},
{"learn":[5.331515983],"iteration":97,"passed_time":0.2644744894,"remaining_time":2.43424479},
{"learn":[5.323861644],"iteration":98,"passed_time":0.265373088,"remaining_time":2.415163155},
{"learn":[5.313277281],"iteration":99,"passed_time":0.2662575238,"remaining_time":2.396317714},
{"learn":[5.30685627],"iteration":100,"passed_time":0.2675544214,"remaining_time":2.381499255},
{"learn":[5.29652059],"iteration":101,"passed_time":0.2687388032,"remaining_time":2.365955346},
{"learn":[5.288350766],"iteration":102,"passed_time":0.2698730463,"remaining_time":2.350253617},
{"learn":[5.27993346],"iteration":103,"passed_time":0.2708540198,"remaining_time":2.333511555},
{"learn":[5.271789139],"iteration":104,"passed_time":0.2721179143,"remaining_time":2.319481269},
{"learn":[5.262684686],"iteration":105,"passed_time":0.273205422,"remaining_time":2.30420422},
{"learn":[5.251619772],"iteration":106,"passed_time":0.2744459535,"remaining_time":2.2904695},
{"learn":[5.241012171],"iteration":107,"passed_time":0.27565001,"remaining_time":2.276664897},
{"learn":[5.232684032],"iteration":108,"passed_time":0.2766486776,"remaining_time":2.261412584},
{"learn":[5.224267141],"iteration":109,"passed_time":0.2776236045,"remaining_time":2.246227346},
{"learn":[5.216324968],"iteration":110,"passed_time":0.2785575165,"remaining_time":2.230969659},
{"learn":[5.211102527],"iteration":111,"passed_time":0.279488431,"remaining_time":2.215943988},
{"learn":[5.206364257],"iteration":112,"passed_time":0.2804127658,"remaining_time":2.201116135},
{"learn":[5.196937641],"iteration":113,"passed_time":0.2814172865,"remaining_time":2.187155402},
{"learn":[5.190746047],"iteration":114,"passed_time":0.2825015846,"remaining_time":2.174033934},
{"learn":[5.181885213],"iteration":115,"passed_time":0.2835363102,"remaining_time":2.160742226},
{"learn":[5.178293568],"iteration":116,"passed_time":0.284267075,"remaining_time":2.145366045},
{"learn":[5.170991438],"iteration":117,"passed_time":0.2856343272,"remaining_time":2.134995564},
{"learn":[5.166257212],"iteration":118,"passed_time":0.2865986428,"remaining_time":2.121793314},
{"learn":[5.161421246],"iteration":119,"passed_time":0.2877509095,"remaining_time":2.110173337},
{"learn":[5.158223542],"iteration":120,"passed_time":0.2887497499,"remaining_time":2.09761182},
{"learn":[5.15470988],"iteration":121,"passed_time":0.2894780655,"remaining_time":2.083292963},
{"learn":[5.146388143],"iteration":122,"passed_time":0.2904252982,"remaining_time":2.070755988},
{"learn":[5.139529364],"iteration":123,"passed_time":0.2915323923,"remaining_time":2.059535287},
{"learn":[5.134276023],"iteration":124,"passed_time":0.2928167684,"remaining_time":2.049717378},
{"learn":[5.128536065],"iteration":125,"passed_time":0.2939798339,"remaining_time":2.039193451},
{"learn":[5.123300353],"iteration":126,"passed_time":0.2948288001,"remaining_time":2.026657815},
{"learn":[5.116200518],"iteration":127,"passed_time":0.2958862651,"remaining_time":2.015725181},
{"learn":[5.108728704],"iteration":128,"passed_time":0.2971447842,"remaining_time":2.006303155},
{"learn":[5.104075866],"iteration":129,"passed_time":0.2982719195,"remaining_time":1.996127461},
{"learn":[5.100317606],"iteration":130,"passed_time":0.2997463017,"remaining_time":1.988393406},
{"learn":[5.095814182],"iteration":131,"passed_time":0.3010428907,"remaining_time":1.979585069},
{"learn":[5.092146915],"iteration":132,"passed_time":0.3019667008,"remaining_time":1.968459621},
{"learn":[5.085258329],"iteration":133,"passed_time":0.3028258813,"remaining_time":1.957068756},
{"learn":[5.079219421],"iteration":134,"passed_time":0.3037819937,"remaining_time":1.946454996},
{"learn":[5.076476829],"iteration":135,"passed_time":0.3048547354,"remaining_time":1.936724202},
{"learn":[5.072133867],"iteration":136,"passed_time":0.3059638561,"remaining_time":1.927348962},
{"learn":[5.067031564],"iteration":137,"passed_time":0.3072057904,"remaining_time":1.918923125},
{"learn":[5.061358312],"iteration":138,"passed_time":0.3081352994,"remaining_time":1.908665416},
{"learn":[5.056759124],"iteration":139,"passed_time":0.308976469,"remaining_time":1.89799831},
{"learn":[5.050254],"iteration":140,"passed_time":0.3098920117,"remaining_time":1.887923674},
{"learn":[5.048376474],"iteration":141,"passed_time":0.3104721241,"remaining_time":1.875951285},
{"learn":[5.042603751],"iteration":142,"passed_time":0.3115832204,"remaining_time":1.867320419},
{"learn":[5.037477349],"iteration":143,"passed_time":0.3131227098,"remaining_time":1.861340553},
{"learn":[5.03230489],"iteration":144,"passed_time":0.3143515982,"remaining_time":1.853590458},
{"learn":[5.025976187],"iteration":145,"passed_time":0.3155186803,"remaining_time":1.845568171},
{"learn":[5.01952451],"iteration":146,"passed_time":0.3166467707,"remaining_time":1.837412894},
{"learn":[5.017569424],"iteration":147,"passed_time":0.3174744623,"remaining_time":1.827623256},
{"learn":[5.008962367],"iteration":148,"passed_time":0.3183422215,"remaining_time":1.818182755},
{"learn":[5.003880266],"iteration":149,"passed_time":0.3194046449,"remaining_time":1.809959654},
{"learn":[4.996387564],"iteration":150,"passed_time":0.320404401,"remaining_time":1.801479049},
{"learn":[4.993361683],"iteration":151,"passed_time":0.3214081837,"remaining_time":1.793119341},
{"learn":[4.99005752],"iteration":152,"passed_time":0.3225280255,"remaining_time":1.785498285},
{"learn":[4.986908764],"iteration":153,"passed_time":0.3235015456,"remaining_time":1.777157841},
{"learn":[4.985207175],"iteration":154,"passed_time":0.324354769,"remaining_time":1.768256644},
{"learn":[4.979003494],"iteration":155,"passed_time":0.325336727,"remaining_time":1.760155113},
{"learn":[4.973142217],"iteration":156,"passed_time":0.3267064838,"remaining_time":1.754226534},
{"learn":[4.967056696],"iteration":157,"passed_time":0.3277340425,"remaining_time":1.746532049},
{"learn":[4.961460696],"iteration":158,"passed_time":0.3287049388,"remaining_time":1.738621721},
{"learn":[4.954240363],"iteration":159,"passed_time":0.3298228527,"remaining_time":1.731569976},
{"learn":[4.952320707],"iteration":160,"passed_time":0.3311036015,"remaining_time":1.725440507},
{"learn":[4.948337777],"iteration":161,"passed_time":0.3321682453,"remaining_time":1.718253022},
{"learn":[4.943228639],"iteration":162,"passed_time":0.3333421673,"remaining_time":1.711701804},
{"learn":[4.938545759],"iteration":163,"passed_time":0.3342738832,"remaining_time":1.703981502},
{"learn":[4.935330572],"iteration":164,"passed_time":0.3353395098,"remaining_time":1.697021156},
{"learn":[4.932051543],"iteration":165,"passed_time":0.336550153,"remaining_time":1.690860407},
{"learn":[4.928964153],"iteration":166,"passed_time":0.3378630659,"remaining_time":1.685269065},
{"learn":[4.922860227],"iteration":167,"passed_time":0.3388600455,"remaining_time":1.678164035},
{"learn":[4.917668772],"iteration":168,"passed_time":0.3398202114,"remaining_time":1.67095027},
{"learn":[4.910365386],"iteration":169,"passed_time":0.3410382947,"remaining_time":1.665069321},
{"learn":[4.906457206],"iteration":170,"passed_time":0.3420780736,"remaining_time":1.658378497},
{"learn":[4.901996508],"iteration":171,"passed_time":0.3432049344,"remaining_time":1.652172591},
{"learn":[4.896816173],"iteration":172,"passed_time":0.3441744249,"remaining_time":1.645273118},
{"learn":[4.891123132],"iteration":173,"passed_time":0.3452501131,"remaining_time":1.638945939},
{"learn":[4.887630202],"iteration":174,"passed_time":0.346328327,"remaining_time":1.632690684},
{"learn":[4.885259712],"iteration":175,"passed_time":0.3472190602,"remaining_time":1.625616509},
{"learn":[4.880659728],"iteration":176,"passed_time":0.3481216287,"remaining_time":1.618667234},
{"learn":[4.877299723],"iteration":177,"passed_time":0.3489611506,"remaining_time":1.611494751},
{"learn":[4.874038772],"iteration":178,"passed_time":0.3500105804,"remaining_time":1.605355791},
{"learn":[4.86943698],"iteration":179,"passed_time":0.3508724101,"remaining_time":1.598418757},
{"learn":[4.861268711],"iteration":180,"passed_time":0.352010519,"remaining_time":1.592798978},
{"learn":[4.858673056],"iteration":181,"passed_time":0.353126592,"remaining_time":1.587129408},
{"learn":[4.854036207],"iteration":182,"passed_time":0.3541720756,"remaining_time":1.581194458},
{"learn":[4.85130244],"iteration":183,"passed_time":0.3556097343,"remaining_time":1.577051865},
{"learn":[4.847510084],"iteration":184,"passed_time":0.3571364153,"remaining_time":1.573330694},
{"learn":[4.845691673],"iteration":185,"passed_time":0.3583060478,"remaining_time":1.568070553},
{"learn":[4.842058646],"iteration":186,"passed_time":0.359807926,"remaining_time":1.56429863},
{"learn":[4.838623675],"iteration":187,"passed_time":0.360940087,"remaining_time":1.558953993},
{"learn":[4.834602161],"iteration":188,"passed_time":0.3621137528,"remaining_time":1.553832029},
{"learn":[4.830858976],"iteration":189,"passed_time":0.3631209039,"remaining_time":1.548041748},
{"learn":[4.827590511],"iteration":190,"passed_time":0.364258388,"remaining_time":1.542853591},
{"learn":[4.822246226],"iteration":191,"passed_time":0.3651830721,"remaining_time":1.536812095},
{"learn":[4.816686395],"iteration":192,"passed_time":0.3663208351,"remaining_time":1.53171458},
{"learn":[4.814797121],"iteration":193,"passed_time":0.3676703241,"remaining_time":1.527537532},
{"learn":[4.811639392],"iteration":194,"passed_time":0.3688019113,"remaining_time":1.522489942},
{"learn":[4.804813432],"iteration":195,"passed_time":0.3698308438,"remaining_time":1.517061217},
{"learn":[4.80251613],"iteration":196,"passed_time":0.3709067408,"remaining_time":1.511868593},
{"learn":[4.800087884],"iteration":197,"passed_time":0.3719453215,"remaining_time":1.506566403},
{"learn":[4.794773135],"iteration":198,"passed_time":0.372952464,"remaining_time":1.501180521},
{"learn":[4.791664833],"iteration":199,"passed_time":0.3739291343,"remaining_time":1.495716537},
{"learn":[4.785989873],"iteration":200,"passed_time":0.3747837869,"remaining_time":1.489812168},
{"learn":[4.782387142],"iteration":201,"passed_time":0.3758165705,"remaining_time":1.484661501},
{"learn":[4.778623704],"iteration":202,"passed_time":0.3769681454,"remaining_time":1.480017792},
{"learn":[4.775772178],"iteration":203,"passed_time":0.3779248275,"remaining_time":1.474647856},
{"learn":[4.77023101],"iteration":204,"passed_time":0.37914701,"remaining_time":1.4703506},
{"learn":[4.764496689],"iteration":205,"passed_time":0.3800524025,"remaining_time":1.464862173},
{"learn":[4.763138716],"iteration":206,"passed_time":0.3812645045,"remaining_time":1.460593005},
{"learn":[4.758053283],"iteration":207,"passed_time":0.3821563286,"remaining_time":1.455133713},
{"learn":[4.755063788],"iteration":208,"passed_time":0.3835788806,"remaining_time":1.451726768},
{"learn":[4.752465267],"iteration":209,"passed_time":0.3847923868,"remaining_time":1.447552312},
{"learn":[4.748067377],"iteration":210,"passed_time":0.3857478106,"remaining_time":1.442440865},
{"learn":[4.744163298],"iteration":211,"passed_time":0.3868369697,"remaining_time":1.437865717},
{"learn":[4.736670896],"iteration":212,"passed_time":0.3880692788,"remaining_time":1.433852218},
{"learn":[4.73349255],"iteration":213,"passed_time":0.3890020655,"remaining_time":1.428764596},
{"learn":[4.731864595],"iteration":214,"passed_time":0.3898465444,"remaining_time":1.423393197},
{"learn":[4.728398311],"iteration":215,"passed_time":0.3913457227,"remaining_time":1.420440031},
{"learn":[4.723865975],"iteration":216,"passed_time":0.3925689608,"remaining_time":1.416504591},
{"learn":[4.723483365],"iteration":217,"passed_time":0.3934115569,"remaining_time":1.411228612},
{"learn":[4.72095416],"iteration":218,"passed_time":0.3944397018,"remaining_time":1.406654827},
{"learn":[4.716173382],"iteration":219,"passed_time":0.3956308324,"remaining_time":1.402691133},
{"learn":[4.710563974],"iteration":220,"passed_time":0.3966546304,"remaining_time":1.398162702},
{"learn":[4.707160263],"iteration":221,"passed_time":0.3977941615,"remaining_time":1.394071431},
{"learn":[4.70408351],"iteration":222,"passed_time":0.3992051501,"remaining_time":1.390952474},
{"learn":[4.702501831],"iteration":223,"passed_time":0.4002621097,"remaining_time":1.386622309},
{"learn":[4.700269738],"iteration":224,"passed_time":0.4011863018,"remaining_time":1.381863928},
{"learn":[4.695346302],"iteration":225,"passed_time":0.4021262426,"remaining_time":1.377193415},
{"learn":[4.689769299],"iteration":226,"passed_time":0.4030107581,"remaining_time":1.372367031},
{"learn":[4.687919514],"iteration":227,"passed_time":0.4039682015,"remaining_time":1.367822156},
{"learn":[4.682982074],"iteration":228,"passed_time":0.4050305328,"remaining_time":1.36366175},
{"learn":[4.679578702],"iteration":229,"passed_time":0.4062035714,"remaining_time":1.359898913},
{"learn":[4.675751423],"iteration":230,"passed_time":0.4073806804,"remaining_time":1.356172048},
{"learn":[4.672710726],"iteration":231,"passed_time":0.4083349081,"remaining_time":1.351729351},
{"learn":[4.6690533],"iteration":232,"passed_time":0.4093688537,"remaining_time":1.347579016},
{"learn":[4.667595702],"iteration":233,"passed_time":0.4107094168,"remaining_time":1.344459031},
{"learn":[4.664241291],"iteration":234,"passed_time":0.4117713792,"remaining_time":1.340447256},
{"learn":[4.662246999],"iteration":235,"passed_time":0.41266042,"remaining_time":1.335900682},
{"learn":[4.658668443],"iteration":236,"passed_time":0.4136815325,"remaining_time":1.331810166},
{"learn":[4.658017572],"iteration":237,"passed_time":0.4146676165,"remaining_time":1.327633293},
{"learn":[4.657656705],"iteration":238,"passed_time":0.4156073472,"remaining_time":1.323335528},
{"learn":[4.653242871],"iteration":239,"passed_time":0.4165724044,"remaining_time":1.319145947},
{"learn":[4.6507302],"iteration":240,"passed_time":0.4176517005,"remaining_time":1.315342907},
{"learn":[4.647671336],"iteration":241,"passed_time":0.4187686666,"remaining_time":1.311680369},
{"learn":[4.645506007],"iteration":242,"passed_time":0.4197327704,"remaining_time":1.307562581},
{"learn":[4.641297906],"iteration":243,"passed_time":0.4206801806,"remaining_time":1.30341892},
{"learn":[4.63798107],"iteration":244,"passed_time":0.4216952359,"remaining_time":1.299509808},
{"learn":[4.635062318],"iteration":245,"passed_time":0.4228506865,"remaining_time":1.296054543},
{"learn":[4.631606017],"iteration":246,"passed_time":0.4239500503,"remaining_time":1.292446914},
{"learn":[4.630215494],"iteration":247,"passed_time":0.4249599987,"remaining_time":1.288588383},
{"learn":[4.62729814],"iteration":248,"passed_time":0.4259099056,"remaining_time":1.284571643},
{"learn":[4.624691756],"iteration":249,"passed_time":0.4269898576,"remaining_time":1.280969573},
{"learn":[4.621840053],"iteration":250,"passed_time":0.4279352495,"remaining_time":1.276986063},
{"learn":[4.619602091],"iteration":251,"passed_time":0.4288454485,"remaining_time":1.272922204},
{"learn":[4.613584029],"iteration":252,"passed_time":0.4299032128,"remaining_time":1.269318972},
{"learn":[4.6119388],"iteration":253,"passed_time":0.4310569457,"remaining_time":1.266017644},
{"learn":[4.60870702],"iteration":254,"passed_time":0.4319687397,"remaining_time":1.262026318},
{"learn":[4.604771557],"iteration":255,"passed_time":0.4329859684,"remaining_time":1.258365471},
{"learn":[4.604231277],"iteration":256,"passed_time":0.4341525284,"remaining_time":1.255156921},
{"learn":[4.600750354],"iteration":257,"passed_time":0.4351720953,"remaining_time":1.251541452},
{"learn":[4.596488253],"iteration":258,"passed_time":0.4364051897,"remaining_time":1.248556933},
{"learn":[4.59470784],"iteration":259,"passed_time":0.4377723874,"remaining_time":1.245967564},
{"learn":[4.588818005],"iteration":260,"passed_time":0.4391188453,"remaining_time":1.243328838},
{"learn":[4.585054174],"iteration":261,"passed_time":0.4401365697,"remaining_time":1.239774002},
{"learn":[4.581471435],"iteration":262,"passed_time":0.4410932815,"remaining_time":1.236067485},
{"learn":[4.577555199],"iteration":263,"passed_time":0.442120513,"remaining_time":1.2325784},
{"learn":[4.57457145],"iteration":264,"passed_time":0.4430698171,"remaining_time":1.228891757},
{"learn":[4.573029224],"iteration":265,"passed_time":0.4440267067,"remaining_time":1.225246627},
{"learn":[4.571326203],"iteration":266,"passed_time":0.4450572115,"remaining_time":1.22182373},
{"learn":[4.571019224],"iteration":267,"passed_time":0.4462818377,"remaining_time":1.2189489},
{"learn":[4.565766631],"iteration":268,"passed_time":0.4472949083,"remaining_time":1.215511442},
{"learn":[4.563383471],"iteration":269,"passed_time":0.44835517,"remaining_time":1.212219534},
{"learn":[4.558165805],"iteration":270,"passed_time":0.4493104639,"remaining_time":1.208661728},
{"learn":[4.55629209],"iteration":271,"passed_time":0.4504633078,"remaining_time":1.205651794},
{"learn":[4.549383848],"iteration":272,"passed_time":0.4517071236,"remaining_time":1.202897725},
{"learn":[4.546227503],"iteration":273,"passed_time":0.4528901573,"remaining_time":1.199993629},
{"learn":[4.540620977],"iteration":274,"passed_time":0.4540821344,"remaining_time":1.197125627},
{"learn":[4.532898237],"iteration":275,"passed_time":0.4549958456,"remaining_time":1.193539827},
{"learn":[4.529757367],"iteration":276,"passed_time":0.456268297,"remaining_time":1.19090967},
{"learn":[4.52579294],"iteration":277,"passed_time":0.4573652844,"remaining_time":1.18783358},
{"learn":[4.521572155],"iteration":278,"passed_time":0.4583699966,"remaining_time":1.184533217},
{"learn":[4.518818099],"iteration":279,"passed_time":0.4594103197,"remaining_time":1.181340822},
{"learn":[4.514012334],"iteration":280,"passed_time":0.4605617027,"remaining_time":1.178447915},
{"learn":[4.508331416],"iteration":281,"passed_time":0.46173439,"remaining_time":1.175621603},
{"learn":[4.506038537],"iteration":282,"passed_time":0.4627078645,"remaining_time":1.172302257},
{"learn":[4.505805643],"iteration":283,"passed_time":0.4636665382,"remaining_time":1.168962117},
{"learn":[4.501550352],"iteration":284,"passed_time":0.4647852617,"remaining_time":1.166040218},
{"learn":[4.494692643],"iteration":285,"passed_time":0.4659920497,"remaining_time":1.163350781},
{"learn":[4.489330245],"iteration":286,"passed_time":0.4670723463,"remaining_time":1.160357432},
{"learn":[4.484826955],"iteration":287,"passed_time":0.4683636177,"remaining_time":1.157898944},
{"learn":[4.478285428],"iteration":288,"passed_time":0.4696213624,"remaining_time":1.155366051},
{"learn":[4.475311671],"iteration":289,"passed_time":0.4705794617,"remaining_time":1.152108337},
{"learn":[4.471581298],"iteration":290,"passed_time":0.471633148,"remaining_time":1.149099319},
{"learn":[4.469164956],"iteration":291,"passed_time":0.4725062195,"remaining_time":1.145665765},
{"learn":[4.462068024],"iteration":292,"passed_time":0.4735500705,"remaining_time":1.142661774},
{"learn":[4.458540976],"iteration":293,"passed_time":0.4746763588,"remaining_time":1.139869079},
{"learn":[4.455757458],"iteration":294,"passed_time":0.4757352022,"remaining_time":1.1369265},
{"learn":[4.453027414],"iteration":295,"passed_time":0.4767397332,"remaining_time":1.133867474},
{"learn":[4.450659338],"iteration":296,"passed_time":0.4776872342,"remaining_time":1.130687292},
{"learn":[4.444696901],"iteration":297,"passed_time":0.4789451722,"remaining_time":1.128253392},
{"learn":[4.442052813],"iteration":298,"passed_time":0.4799297263,"remaining_time":1.125186415},
{"learn":[4.440036756],"iteration":299,"passed_time":0.4809522829,"remaining_time":1.122221994},
{"learn":[4.435017051],"iteration":300,"passed_time":0.4819263275,"remaining_time":1.119157817},
{"learn":[4.429962125],"iteration":301,"passed_time":0.4832487178,"remaining_time":1.116912599},
{"learn":[4.427666256],"iteration":302,"passed_time":0.4841897889,"remaining_time":1.113796313},
{"learn":[4.425030004],"iteration":303,"passed_time":0.4852042533,"remaining_time":1.110862369},
{"learn":[4.422588771],"iteration":304,"passed_time":0.4863976071,"remaining_time":1.108348646},
{"learn":[4.418936667],"iteration":305,"passed_time":0.4875384442,"remaining_time":1.105724445},
{"learn":[4.416887976],"iteration":306,"passed_time":0.488537759,"remaining_time":1.102790446},
{"learn":[4.413773354],"iteration":307,"passed_time":0.4896040075,"remaining_time":1.100019393},
{"learn":[4.411129391],"iteration":308,"passed_time":0.490774876,"remaining_time":1.097493331},
{"learn":[4.40850819],"iteration":309,"passed_time":0.4919698211,"remaining_time":1.095029602},
{"learn":[4.404880292],"iteration":310,"passed_time":0.4933386402,"remaining_time":1.092959238},
{"learn":[4.404593827],"iteration":311,"passed_time":0.4943833445,"remaining_time":1.090178657},
{"learn":[4.402139942],"iteration":312,"passed_time":0.4954539462,"remaining_time":1.08746601},
{"learn":[4.400284725],"iteration":313,"passed_time":0.4966082259,"remaining_time":1.084946634},
{"learn":[4.395805521],"iteration":314,"passed_time":0.4975806458,"remaining_time":1.082040452},
{"learn":[4.392838833],"iteration":315,"passed_time":0.4986083923,"remaining_time":1.079266267},
{"learn":[4.389213061],"iteration":316,"passed_time":0.4999934212,"remaining_time":1.077272892},
{"learn":[4.3861981],"iteration":317,"passed_time":0.5010768704,"remaining_time":1.074636558},
{"learn":[4.385054234],"iteration":318,"passed_time":0.5020884811,"remaining_time":1.071856601},
{"learn":[4.379364607],"iteration":319,"passed_time":0.5030495325,"remaining_time":1.068980256},
{"learn":[4.378387619],"iteration":320,"passed_time":0.5040266592,"remaining_time":1.066149849},
{"learn":[4.375816727],"iteration":321,"passed_time":0.5049248761,"remaining_time":1.063164801},
{"learn":[4.374600202],"iteration":322,"passed_time":0.5060530716,"remaining_time":1.060674704},
{"learn":[4.37098897],"iteration":323,"passed_time":0.5072095962,"remaining_time":1.05825212},
{"learn":[4.367418484],"iteration":324,"passed_time":0.5083624347,"remaining_time":1.055829672},
{"learn":[4.363584638],"iteration":325,"passed_time":0.5093856639,"remaining_time":1.053147047},
{"learn":[4.360770706],"iteration":326,"passed_time":0.5104979832,"remaining_time":1.050657929},
{"learn":[4.358675808],"iteration":327,"passed_time":0.5114712308,"remaining_time":1.047892278},
{"learn":[4.354228195],"iteration":328,"passed_time":0.5125763665,"remaining_time":1.04540651},
{"learn":[4.353773425],"iteration":329,"passed_time":0.5135909437,"remaining_time":1.042745249},
{"learn":[4.351648009],"iteration":330,"passed_time":0.5146084769,"remaining_time":1.040099913},
{"learn":[4.348209927],"iteration":331,"passed_time":0.5157177704,"remaining_time":1.037649008},
{"learn":[4.345852733],"iteration":332,"passed_time":0.516754148,"remaining_time":1.03506011},
{"learn":[4.34237339],"iteration":333,"passed_time":0.5179459245,"remaining_time":1.032790376},
{"learn":[4.340814362],"iteration":334,"passed_time":0.5189475791,"remaining_time":1.030149672},
{"learn":[4.339707068],"iteration":335,"passed_time":0.5200654683,"remaining_time":1.027748425},
{"learn":[4.335430786],"iteration":336,"passed_time":0.5212354054,"remaining_time":1.025457192},
{"learn":[4.33521887],"iteration":337,"passed_time":0.522513877,"remaining_time":1.023385167},
{"learn":[4.328507238],"iteration":338,"passed_time":0.5237134545,"remaining_time":1.021163992},
{"learn":[4.326140732],"iteration":339,"passed_time":0.5247982377,"remaining_time":1.018725991},
{"learn":[4.323785636],"iteration":340,"passed_time":0.5258301393,"remaining_time":1.01619373},
{"learn":[4.320632534],"iteration":341,"passed_time":0.526838822,"remaining_time":1.01362557},
{"learn":[4.31973724],"iteration":342,"passed_time":0.5278992948,"remaining_time":1.011165705},
{"learn":[4.318000924],"iteration":343,"passed_time":0.5289394588,"remaining_time":1.008675247},
{"learn":[4.312713628],"iteration":344,"passed_time":0.530200538,"remaining_time":1.006612616},
{"learn":[4.308220789],"iteration":345,"passed_time":0.5311210503,"remaining_time":1.003910887},
{"learn":[4.305890947],"iteration":346,"passed_time":0.5321804026,"remaining_time":1.0014807},
{"learn":[4.305137856],"iteration":347,"passed_time":0.5332516458,"remaining_time":0.9990806697},
{"learn":[4.304787172],"iteration":348,"passed_time":0.5342084307,"remaining_time":0.9964747518},
{"learn":[4.30350134],"iteration":349,"passed_time":0.5351763723,"remaining_time":0.9938989771},
{"learn":[4.30293809],"iteration":350,"passed_time":0.5363251588,"remaining_time":0.9916667467},
{"learn":[4.299548459],"iteration":351,"passed_time":0.5374568565,"remaining_time":0.9894092131},
{"learn":[4.294768408],"iteration":352,"passed_time":0.5386064648,"remaining_time":0.9871908858},
{"learn":[4.294581479],"iteration":353,"passed_time":0.5395955903,"remaining_time":0.9846857381},
{"learn":[4.292551604],"iteration":354,"passed_time":0.5405541446,"remaining_time":0.9821335866},
{"learn":[4.288628894],"iteration":355,"passed_time":0.5415992782,"remaining_time":0.9797470089},
{"learn":[4.287802767],"iteration":356,"passed_time":0.5424627182,"remaining_time":0.9770406942},
{"learn":[4.284566905],"iteration":357,"passed_time":0.5434333577,"remaining_time":0.9745369152},
{"learn":[4.27890232],"iteration":358,"passed_time":0.5446612989,"remaining_time":0.9725010937},
{"learn":[4.276938023],"iteration":359,"passed_time":0.5458215181,"remaining_time":0.9703493656},
{"learn":[4.273425094],"iteration":360,"passed_time":0.5469774759,"remaining_time":0.9681955875},
{"learn":[4.269726505],"iteration":361,"passed_time":0.5482011993,"remaining_time":0.9661667546},
{"learn":[4.265565857],"iteration":362,"passed_time":0.5495212578,"remaining_time":0.9643114083},
{"learn":[4.262117173],"iteration":363,"passed_time":0.5505109277,"remaining_time":0.9618817308},
{"learn":[4.259185148],"iteration":364,"passed_time":0.5516663904,"remaining_time":0.9597483777},
{"learn":[4.257668507],"iteration":365,"passed_time":0.5526866044,"remaining_time":0.9573860853},
{"learn":[4.253432436],"iteration":366,"passed_time":0.5538424007,"remaining_time":0.9552649582},
{"learn":[4.250216667],"iteration":367,"passed_time":0.5549659578,"remaining_time":0.9530937101},
{"learn":[4.24514828],"iteration":368,"passed_time":0.5560494753,"remaining_time":0.9508596719},
{"learn":[4.244015772],"iteration":369,"passed_time":0.5571105146,"remaining_time":0.9485935789},
{"learn":[4.240329192],"iteration":370,"passed_time":0.5583010054,"remaining_time":0.9465534565},
{"learn":[4.236718014],"iteration":371,"passed_time":0.5598692668,"remaining_time":0.945155644},
{"learn":[4.233495944],"iteration":372,"passed_time":0.5611708362,"remaining_time":0.9433086175},
{"learn":[4.230357491],"iteration":373,"passed_time":0.5622699808,"remaining_time":0.9411256898},
{"learn":[4.227381215],"iteration":374,"passed_time":0.563417976,"remaining_time":0.9390299601},
{"learn":[4.226169067],"iteration":375,"passed_time":0.5645049951,"remaining_time":0.936838077},
{"learn":[4.225963861],"iteration":376,"passed_time":0.5655608431,"remaining_time":0.9346005445},
{"learn":[4.224346548],"iteration":377,"passed_time":0.5666476583,"remaining_time":0.9324202209},
{"learn":[4.222595381],"iteration":378,"passed_time":0.5678263259,"remaining_time":0.9303961698},
{"learn":[4.219700938],"iteration":379,"passed_time":0.5689103655,"remaining_time":0.9282221753},
{"learn":[4.216356207],"iteration":380,"passed_time":0.5700851785,"remaining_time":0.9262013793},
{"learn":[4.214326494],"iteration":381,"passed_time":0.5712056448,"remaining_time":0.9240970902},
{"learn":[4.212901398],"iteration":382,"passed_time":0.5723452559,"remaining_time":0.9220287804},
{"learn":[4.211331091],"iteration":383,"passed_time":0.5733635861,"remaining_time":0.9197707527},
{"learn":[4.208624791],"iteration":384,"passed_time":0.5747268183,"remaining_time":0.9180701123},
{"learn":[4.204659106],"iteration":385,"passed_time":0.5758266844,"remaining_time":0.9159522908},
{"learn":[4.202968852],"iteration":386,"passed_time":0.5770877212,"remaining_time":0.9140950209},
{"learn":[4.197261935],"iteration":387,"passed_time":0.5784182815,"remaining_time":0.9123504853},
{"learn":[4.196934403],"iteration":388,"passed_time":0.5795321177,"remaining_time":0.9102676707},
{"learn":[4.192479929],"iteration":389,"passed_time":0.5809797935,"remaining_time":0.9087119847},
{"learn":[4.190243116],"iteration":390,"passed_time":0.5820152836,"remaining_time":0.9065148535},
{"learn":[4.185852431],"iteration":391,"passed_time":0.5830546289,"remaining_time":0.9043296286},
{"learn":[4.180967944],"iteration":392,"passed_time":0.5840566946,"remaining_time":0.9020926555},
{"learn":[4.178283162],"iteration":393,"passed_time":0.5851886825,"remaining_time":0.9000617807},
{"learn":[4.176341157],"iteration":394,"passed_time":0.5862057564,"remaining_time":0.8978594497},
{"learn":[4.176041504],"iteration":395,"passed_time":0.5872834609,"remaining_time":0.8957555817},
{"learn":[4.175564513],"iteration":396,"passed_time":0.5883319059,"remaining_time":0.8936124415},
{"learn":[4.170830274],"iteration":397,"passed_time":0.5892390988,"remaining_time":0.8912611494},
{"learn":[4.167804808],"iteration":398,"passed_time":0.5903485117,"remaining_time":0.8892216931},
{"learn":[4.165860548],"iteration":399,"passed_time":0.5914274529,"remaining_time":0.8871411793},
{"learn":[4.160950571],"iteration":400,"passed_time":0.5924553966,"remaining_time":0.8849894826},
{"learn":[4.158544115],"iteration":401,"passed_time":0.5935500074,"remaining_time":0.8829425484},
{"learn":[4.154448767],"iteration":402,"passed_time":0.5946475267,"remaining_time":0.8809046487},
{"learn":[4.15197457],"iteration":403,"passed_time":0.5958327245,"remaining_time":0.879000752},
{"learn":[4.149562679],"iteration":404,"passed_time":0.5969598618,"remaining_time":0.8770151056},
{"learn":[4.149327961],"iteration":405,"passed_time":0.5981210011,"remaining_time":0.8750834351},
{"learn":[4.147444889],"iteration":406,"passed_time":0.5991925592,"remaining_time":0.873025031},
{"learn":[4.147254809],"iteration":407,"passed_time":0.60041137,"remaining_time":0.8711851252},
{"learn":[4.144589165],"iteration":408,"passed_time":0.6015265643,"remaining_time":0.8691985318},
{"learn":[4.141691034],"iteration":409,"passed_time":0.6027064078,"remaining_time":0.867309221},
{"learn":[4.138893468],"iteration":410,"passed_time":0.6038115672,"remaining_time":0.8653163336},
{"learn":[4.136964597],"iteration":411,"passed_time":0.6049348391,"remaining_time":0.8633536053},
{"learn":[4.133773523],"iteration":412,"passed_time":0.6061654808,"remaining_time":0.8615475478},
{"learn":[4.131363444],"iteration":413,"passed_time":0.60735398,"remaining_time":0.8596846191},
{"learn":[4.130228592],"iteration":414,"passed_time":0.6083825936,"remaining_time":0.8575995596},
{"learn":[4.12884186],"iteration":415,"passed_time":0.6093935742,"remaining_time":0.8554948253},
{"learn":[4.12413494],"iteration":416,"passed_time":0.6104051806,"remaining_time":0.8533962117},
{"learn":[4.119422508],"iteration":417,"passed_time":0.6116555477,"remaining_time":0.8516352363},
{"learn":[4.117038244],"iteration":418,"passed_time":0.6126783926,"remaining_time":0.8495612079},
{"learn":[4.116067631],"iteration":419,"passed_time":0.6135214908,"remaining_time":0.8472439634},
{"learn":[4.110343455],"iteration":420,"passed_time":0.6145401633,"remaining_time":0.8451751889},
{"learn":[4.105604544],"iteration":421,"passed_time":0.6155402517,"remaining_time":0.8430859371},
{"learn":[4.103390131],"iteration":422,"passed_time":0.616424965,"remaining_time":0.8408444557},
{"learn":[4.096724402],"iteration":423,"passed_time":0.6174280798,"remaining_time":0.8387702216},
{"learn":[4.093431279],"iteration":424,"passed_time":0.6184000043,"remaining_time":0.8366588294},
{"learn":[4.091412744],"iteration":425,"passed_time":0.6194694097,"remaining_time":0.8346841342},
{"learn":[4.091192901],"iteration":426,"passed_time":0.6207302794,"remaining_time":0.8329706091},
{"learn":[4.088994581],"iteration":427,"passed_time":0.6218902217,"remaining_time":0.831124315},
{"learn":[4.087845355],"iteration":428,"passed_time":0.6232275151,"remaining_time":0.8295172754},
{"learn":[4.083650279],"iteration":429,"passed_time":0.6241453453,"remaining_time":0.8273554578},
{"learn":[4.079840652],"iteration":430,"passed_time":0.6252742911,"remaining_time":0.8254781245},
{"learn":[4.075707828],"iteration":431,"passed_time":0.6262074898,"remaining_time":0.8233468848},
{"learn":[4.071345409],"iteration":432,"passed_time":0.6271250865,"remaining_time":0.8212007484},
{"learn":[4.067460475],"iteration":433,"passed_time":0.6281494997,"remaining_time":0.8191995779},
{"learn":[4.064914749],"iteration":434,"passed_time":0.6292025131,"remaining_time":0.8172400457},
{"learn":[4.063823175],"iteration":435,"passed_time":0.6303000844,"remaining_time":0.815342311},
{"learn":[4.058898471],"iteration":436,"passed_time":0.6313475746,"remaining_time":0.8133837174},
{"learn":[4.054120355],"iteration":437,"passed_time":0.6325242248,"remaining_time":0.8115950099},
{"learn":[4.052715901],"iteration":438,"passed_time":0.6337267344,"remaining_time":0.8098421367},
{"learn":[4.052114167],"iteration":439,"passed_time":0.6348075691,"remaining_time":0.8079369061},
{"learn":[4.051377267],"iteration":440,"passed_time":0.6357869293,"remaining_time":0.8059067879},
{"learn":[4.049275336],"iteration":441,"passed_time":0.6368503415,"remaining_time":0.8039875352},
{"learn":[4.047099198],"iteration":442,"passed_time":0.6380885674,"remaining_time":0.8022919459},
{"learn":[4.044348685],"iteration":443,"passed_time":0.6390482133,"remaining_time":0.8002495644},
{"learn":[4.042822379],"iteration":444,"passed_time":0.6400577467,"remaining_time":0.7982742683},
{"learn":[4.041258611],"iteration":445,"passed_time":0.6411411144,"remaining_time":0.7963950166},
{"learn":[4.040044254],"iteration":446,"passed_time":0.6421708612,"remaining_time":0.7944529894},
{"learn":[4.036860137],"iteration":447,"passed_time":0.6431154072,"remaining_time":0.7924100553},
{"learn":[4.036372284],"iteration":448,"passed_time":0.6441613542,"remaining_time":0.7904964502},
{"learn":[4.03368231],"iteration":449,"passed_time":0.6451060509,"remaining_time":0.7884629511},
{"learn":[4.032439519],"iteration":450,"passed_time":0.6460908032,"remaining_time":0.7864830398},
{"learn":[4.032008634],"iteration":451,"passed_time":0.647181325,"remaining_time":0.7846357658},
{"learn":[4.030034932],"iteration":452,"passed_time":0.6484231969,"remaining_time":0.7829745888},
{"learn":[4.028173412],"iteration":453,"passed_time":0.6493981272,"remaining_time":0.7809942235},
{"learn":[4.023806097],"iteration":454,"passed_time":0.6503758678,"remaining_time":0.7790216438},
{"learn":[4.020239186],"iteration":455,"passed_time":0.6513550382,"remaining_time":0.7770551333},
{"learn":[4.017384838],"iteration":456,"passed_time":0.6524096592,"remaining_time":0.7751825929},
{"learn":[4.016468229],"iteration":457,"passed_time":0.6533903729,"remaining_time":0.7732261618},
{"learn":[4.014530169],"iteration":458,"passed_time":0.6544600962,"remaining_time":0.7713788933},
{"learn":[4.012884822],"iteration":459,"passed_time":0.6554486242,"remaining_time":0.7694396893},
{"learn":[4.008924707],"iteration":460,"passed_time":0.6564914216,"remaining_time":0.7675680613},
{"learn":[4.008286778],"iteration":461,"passed_time":0.6574192076,"remaining_time":0.7655660902},
{"learn":[4.006444202],"iteration":462,"passed_time":0.6585580661,"remaining_time":0.763813567},
{"learn":[4.003284363],"iteration":463,"passed_time":0.6596032315,"remaining_time":0.7619554571},
{"learn":[3.999811484],"iteration":464,"passed_time":0.6609383141,"remaining_time":0.7604344044},
{"learn":[3.997483319],"iteration":465,"passed_time":0.6621448193,"remaining_time":0.75876681},
{"learn":[3.99708333],"iteration":466,"passed_time":0.663021116,"remaining_time":0.7567243145},
{"learn":[3.995860263],"iteration":467,"passed_time":0.6639783166,"remaining_time":0.7547787701},
{"learn":[3.994131111],"iteration":468,"passed_time":0.6648809391,"remaining_time":0.7527756475},
{"learn":[3.993125499],"iteration":469,"passed_time":0.6657515139,"remaining_time":0.7507410689},
{"learn":[3.992954084],"iteration":470,"passed_time":0.6668559268,"remaining_time":0.7489740664},
{"learn":[3.990635743],"iteration":471,"passed_time":0.667925564,"remaining_time":0.7471709699},
{"learn":[3.986678254],"iteration":472,"passed_time":0.6688851492,"remaining_time":0.7452483586},
{"learn":[3.986393291],"iteration":473,"passed_time":0.669855785,"remaining_time":0.7433420736},
{"learn":[3.986152671],"iteration":474,"passed_time":0.6709474064,"remaining_time":0.7415734492},
{"learn":[3.985596662],"iteration":475,"passed_time":0.6718422426,"remaining_time":0.7395910402},
{"learn":[3.983853457],"iteration":476,"passed_time":0.6727229533,"remaining_time":0.7375977035},
{"learn":[3.983263928],"iteration":477,"passed_time":0.6737481018,"remaining_time":0.7357667555},
{"learn":[3.980067202],"iteration":478,"passed_time":0.6750788635,"remaining_time":0.7342715823},
{"learn":[3.978115407],"iteration":479,"passed_time":0.6759713972,"remaining_time":0.732302347},
{"learn":[3.972661644],"iteration":480,"passed_time":0.6770368687,"remaining_time":0.7305241889},
{"learn":[3.969938254],"iteration":481,"passed_time":0.6779638584,"remaining_time":0.7286001632},
{"learn":[3.968211434],"iteration":482,"passed_time":0.6788593681,"remaining_time":0.72664657},
{"learn":[3.966113368],"iteration":483,"passed_time":0.6799507451,"remaining_time":0.7249061662},
{"learn":[3.962246044],"iteration":484,"passed_time":0.6811002575,"remaining_time":0.7232301704},
{"learn":[3.961319703],"iteration":485,"passed_time":0.6822458232,"remaining_time":0.7215521669},
{"learn":[3.96078191],"iteration":486,"passed_time":0.6833663801,"remaining_time":0.7198500062},
{"learn":[3.958913633],"iteration":487,"passed_time":0.6843789817,"remaining_time":0.7180369644},
{"learn":[3.957428286],"iteration":488,"passed_time":0.6854150593,"remaining_time":0.7162517287},
{"learn":[3.952641965],"iteration":489,"passed_time":0.6863684518,"remaining_time":0.7143834906},
{"learn":[3.951486786],"iteration":490,"passed_time":0.6873144069,"remaining_time":0.712511269},
{"learn":[3.94938344],"iteration":491,"passed_time":0.6883490944,"remaining_time":0.7107344308},
{"learn":[3.947297924],"iteration":492,"passed_time":0.6894177512,"remaining_time":0.7089955372},
{"learn":[3.946284886],"iteration":493,"passed_time":0.6903853005,"remaining_time":0.7071557936},
{"learn":[3.943288204],"iteration":494,"passed_time":0.691291291,"remaining_time":0.7052567717},
{"learn":[3.943076488],"iteration":495,"passed_time":0.6921386827,"remaining_time":0.7033022098},
{"learn":[3.942347078],"iteration":496,"passed_time":0.6929852837,"remaining_time":0.7013513032},
{"learn":[3.940251541],"iteration":497,"passed_time":0.6940095968,"remaining_time":0.699583971},
{"learn":[3.939011019],"iteration":498,"passed_time":0.6950003763,"remaining_time":0.6977859489},
{"learn":[3.938760512],"iteration":499,"passed_time":0.6958210769,"remaining_time":0.6958210769},
{"learn":[3.934522727],"iteration":500,"passed_time":0.6967156759,"remaining_time":0.6939343758},
{"learn":[3.930091193],"iteration":501,"passed_time":0.6978157208,"remaining_time":0.6922554362},
{"learn":[3.927671752],"iteration":502,"passed_time":0.6987286921,"remaining_time":0.6903939562},
{"learn":[3.927280041],"iteration":503,"passed_time":0.6997070942,"remaining_time":0.6886006324},
{"learn":[3.925987561],"iteration":504,"passed_time":0.7006246379,"remaining_time":0.6867508827},
{"learn":[3.921645957],"iteration":505,"passed_time":0.7016193536,"remaining_time":0.6849801594},
{"learn":[3.920333743],"iteration":506,"passed_time":0.7025737028,"remaining_time":0.6831732455},
{"learn":[3.918659461],"iteration":507,"passed_time":0.7034917535,"remaining_time":0.6813345329},
{"learn":[3.916124385],"iteration":508,"passed_time":0.7044882517,"remaining_time":0.6795751111},
{"learn":[3.913849268],"iteration":509,"passed_time":0.7056335024,"remaining_time":0.6779616003},
{"learn":[3.912826119],"iteration":510,"passed_time":0.7066052871,"remaining_time":0.6761839244},
{"learn":[3.910034145],"iteration":511,"passed_time":0.707578562,"remaining_time":0.6744108169},
{"learn":[3.90792379],"iteration":512,"passed_time":0.7085672612,"remaining_time":0.6726554702},
{"learn":[3.907823851],"iteration":513,"passed_time":0.7095065922,"remaining_time":0.6708564276},
{"learn":[3.904527401],"iteration":514,"passed_time":0.7108895317,"remaining_time":0.669478491},
{"learn":[3.903378283],"iteration":515,"passed_time":0.712004384,"remaining_time":0.6678490734},
{"learn":[3.902170135],"iteration":516,"passed_time":0.7128434052,"remaining_time":0.665963955},
{"learn":[3.899435429],"iteration":517,"passed_time":0.7139376878,"remaining_time":0.6643203968},
{"learn":[3.897497505],"iteration":518,"passed_time":0.7148570566,"remaining_time":0.6625168482},
{"learn":[3.896426119],"iteration":519,"passed_time":0.7158770092,"remaining_time":0.6608095469},
{"learn":[3.896044669],"iteration":520,"passed_time":0.7169276446,"remaining_time":0.6591330936},
{"learn":[3.892795942],"iteration":521,"passed_time":0.7179167011,"remaining_time":0.6574026496},
{"learn":[3.892413888],"iteration":522,"passed_time":0.718876429,"remaining_time":0.6556482918},
{"learn":[3.891738985],"iteration":523,"passed_time":0.7198226206,"remaining_time":0.6538846706},
{"learn":[3.88822057],"iteration":524,"passed_time":0.7207849223,"remaining_time":0.6521387392},
{"learn":[3.883837053],"iteration":525,"passed_time":0.7217849727,"remaining_time":0.6504298043},
{"learn":[3.881769742],"iteration":526,"passed_time":0.7227740248,"remaining_time":0.6487136883},
{"learn":[3.880356898],"iteration":527,"passed_time":0.7236737786,"remaining_time":0.6469204991},
{"learn":[3.879250273],"iteration":528,"passed_time":0.7245463877,"remaining_time":0.6451065191},
{"learn":[3.877174493],"iteration":529,"passed_time":0.7255024727,"remaining_time":0.6433701173},
{"learn":[3.875854201],"iteration":530,"passed_time":0.7266487206,"remaining_time":0.6418046138},
{"learn":[3.873189396],"iteration":531,"passed_time":0.7279287935,"remaining_time":0.6403584123},
{"learn":[3.871583368],"iteration":532,"passed_time":0.7292331331,"remaining_time":0.638934096},
{"learn":[3.869622679],"iteration":533,"passed_time":0.7302004532,"remaining_time":0.6372161259},
{"learn":[3.866860164],"iteration":534,"passed_time":0.7312585178,"remaining_time":0.6355798332},
{"learn":[3.864498444],"iteration":535,"passed_time":0.7322678013,"remaining_time":0.6339034698},
{"learn":[3.861416322],"iteration":536,"passed_time":0.7331015969,"remaining_time":0.6320782856},
{"learn":[3.860265769],"iteration":537,"passed_time":0.7340158235,"remaining_time":0.6303258559},
{"learn":[3.859328725],"iteration":538,"passed_time":0.7348789182,"remaining_time":0.6285328039},
{"learn":[3.858521278],"iteration":539,"passed_time":0.7360208906,"remaining_time":0.6269807587},
{"learn":[3.85599111],"iteration":540,"passed_time":0.7371806204,"remaining_time":0.6254452953},
{"learn":[3.852379816],"iteration":541,"passed_time":0.738228915,"remaining_time":0.6238170536},
{"learn":[3.851327537],"iteration":542,"passed_time":0.7391517212,"remaining_time":0.6220853344},
{"learn":[3.847854898],"iteration":543,"passed_time":0.7400535017,"remaining_time":0.6203389647},
{"learn":[3.847083414],"iteration":544,"passed_time":0.7409852049,"remaining_time":0.6186206756},
{"learn":[3.845397429],"iteration":545,"passed_time":0.7419248228,"remaining_time":0.616911849},
{"learn":[3.841933528],"iteration":546,"passed_time":0.742893068,"remaining_time":0.6152295426},
{"learn":[3.840996474],"iteration":547,"passed_time":0.7442359353,"remaining_time":0.6138588371},
{"learn":[3.838355966],"iteration":548,"passed_time":0.7452425407,"remaining_time":0.6122119961},
{"learn":[3.83342799],"iteration":549,"passed_time":0.746121615,"remaining_time":0.6104631396},
{"learn":[3.828161535],"iteration":550,"passed_time":0.747137527,"remaining_time":0.6088289467},
{"learn":[3.823502399],"iteration":551,"passed_time":0.748109228,"remaining_time":0.6071611125},
{"learn":[3.820068862],"iteration":552,"passed_time":0.7489696135,"remaining_time":0.6054058178},
{"learn":[3.817951642],"iteration":553,"passed_time":0.7498414006,"remaining_time":0.6036629326},
{"learn":[3.815785958],"iteration":554,"passed_time":0.7507351136,"remaining_time":0.6019407667},
{"learn":[3.81503012],"iteration":555,"passed_time":0.7515954347,"remaining_time":0.6001949155},
{"learn":[3.813529315],"iteration":556,"passed_time":0.7525242222,"remaining_time":0.5985066973},
{"learn":[3.808881326],"iteration":557,"passed_time":0.7533925698,"remaining_time":0.5967733259},
{"learn":[3.808740434],"iteration":558,"passed_time":0.7543724138,"remaining_time":0.5951310098},
{"learn":[3.80714352],"iteration":559,"passed_time":0.7555610921,"remaining_time":0.5936551438},
{"learn":[3.80573346],"iteration":560,"passed_time":0.756425585,"remaining_time":0.5919266164},
{"learn":[3.803370052],"iteration":561,"passed_time":0.7573269078,"remaining_time":0.5902298676},
{"learn":[3.803215211],"iteration":562,"passed_time":0.7582639693,"remaining_time":0.5885636849},
{"learn":[3.801309667],"iteration":563,"passed_time":0.759345685,"remaining_time":0.5870119125},
{"learn":[3.800003847],"iteration":564,"passed_time":0.7603402933,"remaining_time":0.5853947391},
{"learn":[3.798026138],"iteration":565,"passed_time":0.7613053929,"remaining_time":0.5837571387},
{"learn":[3.794745847],"iteration":566,"passed_time":0.7622591197,"remaining_time":0.5821132254},
{"learn":[3.794312041],"iteration":567,"passed_time":0.7631254427,"remaining_time":0.5804052663},
{"learn":[3.792205926],"iteration":568,"passed_time":0.7640301172,"remaining_time":0.5787293155},
{"learn":[3.788991061],"iteration":569,"passed_time":0.7649390172,"remaining_time":0.5770592586},
{"learn":[3.787391572],"iteration":570,"passed_time":0.7658452826,"remaining_time":0.5753898884},
{"learn":[3.7826445],"iteration":571,"passed_time":0.7668001753,"remaining_time":0.5737595717},
{"learn":[3.781700331],"iteration":572,"passed_time":0.7680680373,"remaining_time":0.5723648376},
{"learn":[3.780045374],"iteration":573,"passed_time":0.7690183813,"remaining_time":0.5707348962},
{"learn":[3.775462644],"iteration":574,"passed_time":0.7699091972,"remaining_time":0.5690633197},
{"learn":[3.773711943],"iteration":575,"passed_time":0.7708377481,"remaining_time":0.5674222313},
{"learn":[3.772415806],"iteration":576,"passed_time":0.7717333433,"remaining_time":0.5657594527},
{"learn":[3.770170875],"iteration":577,"passed_time":0.7727416691,"remaining_time":0.5641816338},
{"learn":[3.765166479],"iteration":578,"passed_time":0.7736073035,"remaining_time":0.562502029},
{"learn":[3.763976102],"iteration":579,"passed_time":0.7746452687,"remaining_time":0.5609500222},
{"learn":[3.760761708],"iteration":580,"passed_time":0.77546681,"remaining_time":0.5592437063},
{"learn":[3.758155662],"iteration":581,"passed_time":0.7764185918,"remaining_time":0.5576339714},
{"learn":[3.756844548],"iteration":582,"passed_time":0.7773149856,"remaining_time":0.5559868765},
{"learn":[3.753098923],"iteration":583,"passed_time":0.7781135686,"remaining_time":0.554272679},
{"learn":[3.751618946],"iteration":584,"passed_time":0.7791488426,"remaining_time":0.5527295208},
{"learn":[3.751398464],"iteration":585,"passed_time":0.7800811532,"remaining_time":0.551115354},
{"learn":[3.749920103],"iteration":586,"passed_time":0.7811270452,"remaining_time":0.5495834236},
{"learn":[3.748237465],"iteration":587,"passed_time":0.7821411126,"remaining_time":0.5480308476},
{"learn":[3.746021536],"iteration":588,"passed_time":0.7833814903,"remaining_time":0.5466380178},
{"learn":[3.74417648],"iteration":589,"passed_time":0.7844430319,"remaining_time":0.545121429},
{"learn":[3.738788389],"iteration":590,"passed_time":0.7853970315,"remaining_time":0.5435319558},
{"learn":[3.736021611],"iteration":591,"passed_time":0.7863428111,"remaining_time":0.5419389644},
{"learn":[3.734546151],"iteration":592,"passed_time":0.7872829231,"remaining_time":0.540344266},
{"learn":[3.733527479],"iteration":593,"passed_time":0.7882097383,"remaining_time":0.5387426831},
{"learn":[3.733026392],"iteration":594,"passed_time":0.7893584949,"remaining_time":0.5372944377},
{"learn":[3.730314752],"iteration":595,"passed_time":0.7906812735,"remaining_time":0.5359651585},
{"learn":[3.727342596],"iteration":596,"passed_time":0.7916435218,"remaining_time":0.5343925281},
{"learn":[3.725459604],"iteration":597,"passed_time":0.7925415232,"remaining_time":0.5327787497},
{"learn":[3.723158842],"iteration":598,"passed_time":0.7935340141,"remaining_time":0.5312306171},
{"learn":[3.722362756],"iteration":599,"passed_time":0.7944844248,"remaining_time":0.5296562832},
{"learn":[3.721443615],"iteration":600,"passed_time":0.795364917,"remaining_time":0.5280376071},
{"learn":[3.720743486],"iteration":601,"passed_time":0.7963545893,"remaining_time":0.5264935657},
{"learn":[3.720215334],"iteration":602,"passed_time":0.7973189316,"remaining_time":0.5249346863},
{"learn":[3.719436563],"iteration":603,"passed_time":0.7987983029,"remaining_time":0.5237154436},
{"learn":[3.715046574],"iteration":604,"passed_time":0.7997766186,"remaining_time":0.5221682055},
{"learn":[3.71443396],"iteration":605,"passed_time":0.8007639042,"remaining_time":0.520628677},
{"learn":[3.712938941],"iteration":606,"passed_time":0.8017138635,"remaining_time":0.5190668013},
{"learn":[3.712814764],"iteration":607,"passed_time":0.8026918583,"remaining_time":0.5175250139},
{"learn":[3.71235348],"iteration":608,"passed_time":0.8037134879,"remaining_time":0.5160130932},
{"learn":[3.711223749],"iteration":609,"passed_time":0.8047083087,"remaining_time":0.51448564},
{"learn":[3.710755648],"iteration":610,"passed_time":0.8057811832,"remaining_time":0.513009624},
{"learn":[3.708668039],"iteration":611,"passed_time":0.8067003775,"remaining_time":0.5114374943},
{"learn":[3.705623591],"iteration":612,"passed_time":0.8076504176,"remaining_time":0.5098869684},
{"learn":[3.704045802],"iteration":613,"passed_time":0.8087115786,"remaining_time":0.5084082563},
{"learn":[3.699915209],"iteration":614,"passed_time":0.8097084664,"remaining_time":0.506890666},
{"learn":[3.696182221],"iteration":615,"passed_time":0.8106983155,"remaining_time":0.5053703785},
{"learn":[3.694263278],"iteration":616,"passed_time":0.811533993,"remaining_time":0.5037561091},
{"learn":[3.693810229],"iteration":617,"passed_time":0.8124485829,"remaining_time":0.502193137},
{"learn":[3.690900932],"iteration":618,"passed_time":0.8134024537,"remaining_time":0.5006564376},
{"learn":[3.688020895],"iteration":619,"passed_time":0.8143714405,"remaining_time":0.4991308829},
{"learn":[3.685491894],"iteration":620,"passed_time":0.815356518,"remaining_time":0.497616941},
{"learn":[3.684328128],"iteration":621,"passed_time":0.8166327005,"remaining_time":0.496281609},
{"learn":[3.680640153],"iteration":622,"passed_time":0.8177286401,"remaining_time":0.4948373954},
{"learn":[3.678932783],"iteration":623,"passed_time":0.8188152865,"remaining_time":0.4933886983},
{"learn":[3.674167041],"iteration":624,"passed_time":0.8197483885,"remaining_time":0.4918490331},
{"learn":[3.672200976],"iteration":625,"passed_time":0.8211652562,"remaining_time":0.4906003288},
{"learn":[3.670606604],"iteration":626,"passed_time":0.8221483465,"remaining_time":0.4890930355},
{"learn":[3.665506042],"iteration":627,"passed_time":0.8230939696,"remaining_time":0.4875652177},
{"learn":[3.664214007],"iteration":628,"passed_time":0.8240015075,"remaining_time":0.4860167874},
{"learn":[3.66261643],"iteration":629,"passed_time":0.8248903995,"remaining_time":0.484459441},
{"learn":[3.662118449],"iteration":630,"passed_time":0.8258851252,"remaining_time":0.4829661033},
{"learn":[3.660871366],"iteration":631,"passed_time":0.8268338302,"remaining_time":0.4814475467},
{"learn":[3.656695243],"iteration":632,"passed_time":0.8278152447,"remaining_time":0.4799497548},
{"learn":[3.654497801],"iteration":633,"passed_time":0.8287349381,"remaining_time":0.4784179611},
{"learn":[3.654189134],"iteration":634,"passed_time":0.8299360285,"remaining_time":0.4770498432},
{"learn":[3.653957699],"iteration":635,"passed_time":0.8307306339,"remaining_time":0.4754496081},
{"learn":[3.651920725],"iteration":636,"passed_time":0.8317785676,"remaining_time":0.4739962638},
{"learn":[3.65106705],"iteration":637,"passed_time":0.8326760342,"remaining_time":0.4724588157},
{"learn":[3.650612844],"iteration":638,"passed_time":0.8335655895,"remaining_time":0.4709189011},
{"learn":[3.649884732],"iteration":639,"passed_time":0.8344880004,"remaining_time":0.4693995002},
{"learn":[3.646276182],"iteration":640,"passed_time":0.8357260315,"remaining_time":0.468058729},
{"learn":[3.645808194],"iteration":641,"passed_time":0.8367251538,"remaining_time":0.4665850546},
{"learn":[3.645042989],"iteration":642,"passed_time":0.837727472,"remaining_time":0.4651146306},
{"learn":[3.639864499],"iteration":643,"passed_time":0.8386361387,"remaining_time":0.4635938904},
{"learn":[3.637318478],"iteration":644,"passed_time":0.8395794056,"remaining_time":0.4620940915},
{"learn":[3.636344905],"iteration":645,"passed_time":0.8405306547,"remaining_time":0.4606003897},
{"learn":[3.634754643],"iteration":646,"passed_time":0.841527841,"remaining_time":0.459133428},
{"learn":[3.630724975],"iteration":647,"passed_time":0.8425135634,"remaining_time":0.4576616888},
{"learn":[3.629408252],"iteration":648,"passed_time":0.8435996647,"remaining_time":0.4562457355},
{"learn":[3.62790646],"iteration":649,"passed_time":0.8445085233,"remaining_time":0.4547353587},
{"learn":[3.627388973],"iteration":650,"passed_time":0.8455124352,"remaining_time":0.4532777878},
{"learn":[3.625163557],"iteration":651,"passed_time":0.8464920946,"remaining_time":0.451808664},
{"learn":[3.623701985],"iteration":652,"passed_time":0.8474785509,"remaining_time":0.4503446511},
{"learn":[3.622342639],"iteration":653,"passed_time":0.84838722,"remaining_time":0.4488409452},
{"learn":[3.621130639],"iteration":654,"passed_time":0.849450382,"remaining_time":0.4474204302},
{"learn":[3.619125665],"iteration":655,"passed_time":0.8503972148,"remaining_time":0.4459400029},
{"learn":[3.618878783],"iteration":656,"passed_time":0.851787508,"remaining_time":0.4446927173},
{"learn":[3.616207429],"iteration":657,"passed_time":0.8528189395,"remaining_time":0.4432584762},
{"learn":[3.61206486],"iteration":658,"passed_time":0.8536900544,"remaining_time":0.4417425016},
{"learn":[3.611955873],"iteration":659,"passed_time":0.8546420227,"remaining_time":0.4402701329},
{"learn":[3.610713743],"iteration":660,"passed_time":0.8556540585,"remaining_time":0.438830145},
{"learn":[3.610044025],"iteration":661,"passed_time":0.8564731248,"remaining_time":0.4372929247},
{"learn":[3.607342669],"iteration":662,"passed_time":0.8573923114,"remaining_time":0.4358087616},
{"learn":[3.602510618],"iteration":663,"passed_time":0.858721949,"remaining_time":0.4345339983},
{"learn":[3.600492392],"iteration":664,"passed_time":0.8597849642,"remaining_time":0.4331247564},
{"learn":[3.597171065],"iteration":665,"passed_time":0.8607999867,"remaining_time":0.4316924858},
{"learn":[3.594358798],"iteration":666,"passed_time":0.8617595392,"remaining_time":0.4302337729},
{"learn":[3.593945251],"iteration":667,"passed_time":0.8626984919,"remaining_time":0.4287663163},
{"learn":[3.593607748],"iteration":668,"passed_time":0.8635081675,"remaining_time":0.4272364775},
{"learn":[3.592238714],"iteration":669,"passed_time":0.864598595,"remaining_time":0.4258470692},
{"learn":[3.590144654],"iteration":670,"passed_time":0.8655663735,"remaining_time":0.4243984156},
{"learn":[3.587151536],"iteration":671,"passed_time":0.8664769548,"remaining_time":0.4229232756},
{"learn":[3.586070865],"iteration":672,"passed_time":0.8674834491,"remaining_time":0.4214964158},
{"learn":[3.585102746],"iteration":673,"passed_time":0.8686196755,"remaining_time":0.4201335522},
{"learn":[3.584362847],"iteration":674,"passed_time":0.8696068544,"remaining_time":0.4186995965},
{"learn":[3.581407561],"iteration":675,"passed_time":0.8706427595,"remaining_time":0.4172903167},
{"learn":[3.57919422],"iteration":676,"passed_time":0.8715895643,"remaining_time":0.4158396296},
{"learn":[3.577632204],"iteration":677,"passed_time":0.8725363053,"remaining_time":0.4143903987},
{"learn":[3.573911195],"iteration":678,"passed_time":0.8734867257,"remaining_time":0.4129443873},
{"learn":[3.573408216],"iteration":679,"passed_time":0.8745223567,"remaining_time":0.4115399325},
{"learn":[3.571076482],"iteration":680,"passed_time":0.8756498963,"remaining_time":0.4101796137},
{"learn":[3.568177107],"iteration":681,"passed_time":0.8765800165,"remaining_time":0.4087279256},
{"learn":[3.564824621],"iteration":682,"passed_time":0.877530182,"remaining_time":0.4072870684},
{"learn":[3.562475026],"iteration":683,"passed_time":0.8787554971,"remaining_time":0.4059747618},
{"learn":[3.561226889],"iteration":684,"passed_time":0.8796370255,"remaining_time":0.4045046176},
{"learn":[3.559383467],"iteration":685,"passed_time":0.8806347026,"remaining_time":0.4030893537},
{"learn":[3.555209766],"iteration":686,"passed_time":0.8816158956,"remaining_time":0.4016677952},
{"learn":[3.55345383],"iteration":687,"passed_time":0.8826103358,"remaining_time":0.4002535244},
{"learn":[3.552300968],"iteration":688,"passed_time":0.8835567108,"remaining_time":0.3988187766},
{"learn":[3.551253986],"iteration":689,"passed_time":0.8845094384,"remaining_time":0.3973882984},
{"learn":[3.549807725],"iteration":690,"passed_time":0.8854646987,"remaining_time":0.3959603356},
{"learn":[3.547992926],"iteration":691,"passed_time":0.886409718,"remaining_time":0.3945291809},
{"learn":[3.545438607],"iteration":692,"passed_time":0.8874417934,"remaining_time":0.3931379951},
{"learn":[3.543313763],"iteration":693,"passed_time":0.8885258771,"remaining_time":0.3917707758},
{"learn":[3.542962896],"iteration":694,"passed_time":0.8895643817,"remaining_time":0.3903843689},
{"learn":[3.539800465],"iteration":695,"passed_time":0.8904160501,"remaining_time":0.3889173552},
{"learn":[3.53953187],"iteration":696,"passed_time":0.8915394104,"remaining_time":0.3875702171},
{"learn":[3.536332425],"iteration":697,"passed_time":0.8924228526,"remaining_time":0.3861199162},
{"learn":[3.534993327],"iteration":698,"passed_time":0.8934237984,"remaining_time":0.3847218359},
{"learn":[3.531637011],"iteration":699,"passed_time":0.8943638106,"remaining_time":0.383298776},
{"learn":[3.531040284],"iteration":700,"passed_time":0.8952072491,"remaining_time":0.3818359022},
{"learn":[3.529973872],"iteration":701,"passed_time":0.8961320089,"remaining_time":0.3804093143},
{"learn":[3.527325183],"iteration":702,"passed_time":0.8971943999,"remaining_time":0.3790422998},
{"learn":[3.527200815],"iteration":703,"passed_time":0.8980905656,"remaining_time":0.3776062605},
{"learn":[3.523459911],"iteration":704,"passed_time":0.8990406236,"remaining_time":0.3761943035},
{"learn":[3.522729934],"iteration":705,"passed_time":0.8999823239,"remaining_time":0.3747801745},
{"learn":[3.522260582],"iteration":706,"passed_time":0.9009241163,"remaining_time":0.3733674202},
{"learn":[3.518641591],"iteration":707,"passed_time":0.9017911716,"remaining_time":0.3719251724},
{"learn":[3.516856405],"iteration":708,"passed_time":0.9027004485,"remaining_time":0.3705018766},
{"learn":[3.515083413],"iteration":709,"passed_time":0.903725246,"remaining_time":0.3691272131},
{"learn":[3.514671214],"iteration":710,"passed_time":0.904667064,"remaining_time":0.3677198052},
{"learn":[3.512617621],"iteration":711,"passed_time":0.905609677,"remaining_time":0.3663140267},
{"learn":[3.510747971],"iteration":712,"passed_time":0.9067345462,"remaining_time":0.3649829099},
{"learn":[3.508149266],"iteration":713,"passed_time":0.9077337929,"remaining_time":0.3636020515},
{"learn":[3.504557165],"iteration":714,"passed_time":0.9086709021,"remaining_time":0.3621974924},
{"learn":[3.501367208],"iteration":715,"passed_time":0.9095594141,"remaining_time":0.3607749632},
{"learn":[3.497593362],"iteration":716,"passed_time":0.9105159158,"remaining_time":0.359380759},
{"learn":[3.496291169],"iteration":717,"passed_time":0.911420652,"remaining_time":0.3579674427},
{"learn":[3.49330374],"iteration":718,"passed_time":0.9124179635,"remaining_time":0.3565917215},
{"learn":[3.490044385],"iteration":719,"passed_time":0.9135044521,"remaining_time":0.3552517314},
{"learn":[3.488891789],"iteration":720,"passed_time":0.9144008479,"remaining_time":0.3538388857},
{"learn":[3.486869081],"iteration":721,"passed_time":0.9152162476,"remaining_time":0.3523962837},
{"learn":[3.486303638],"iteration":722,"passed_time":0.9161473739,"remaining_time":0.3509997546},
{"learn":[3.486035862],"iteration":723,"passed_time":0.9169861902,"remaining_time":0.3495693211},
{"learn":[3.482668951],"iteration":724,"passed_time":0.9178588171,"remaining_time":0.3481533444},
{"learn":[3.47820549],"iteration":725,"passed_time":0.918698797,"remaining_time":0.3467265432},
{"learn":[3.474392283],"iteration":726,"passed_time":0.9196916278,"remaining_time":0.3453587543},
{"learn":[3.472268163],"iteration":727,"passed_time":0.9207615523,"remaining_time":0.3440207998},
{"learn":[3.471209164],"iteration":728,"passed_time":0.9216703255,"remaining_time":0.3426236738},
{"learn":[3.470049971],"iteration":729,"passed_time":0.922660617,"remaining_time":0.3412580364},
{"learn":[3.469078654],"iteration":730,"passed_time":0.9235165499,"remaining_time":0.3398439835},
{"learn":[3.468643292],"iteration":731,"passed_time":0.9245022876,"remaining_time":0.3384789796},
{"learn":[3.468134848],"iteration":732,"passed_time":0.9254120019,"remaining_time":0.3370873186},
{"learn":[3.467820182],"iteration":733,"passed_time":0.926331744,"remaining_time":0.3357006048},
{"learn":[3.465776156],"iteration":734,"passed_time":0.9272595276,"remaining_time":0.334318061},
{"learn":[3.463037608],"iteration":735,"passed_time":0.9284115755,"remaining_time":0.3330171956},
{"learn":[3.45965637],"iteration":736,"passed_time":0.9293451549,"remaining_time":0.331638773},
{"learn":[3.457275091],"iteration":737,"passed_time":0.9302729752,"remaining_time":0.3302595115},
{"learn":[3.455522955],"iteration":738,"passed_time":0.9312027878,"remaining_time":0.3288821754},
{"learn":[3.451270508],"iteration":739,"passed_time":0.9323089197,"remaining_time":0.3275679988},
{"learn":[3.450978947],"iteration":740,"passed_time":0.9333611465,"remaining_time":0.3262355424},
{"learn":[3.450608492],"iteration":741,"passed_time":0.9343013966,"remaining_time":0.3248649061},
{"learn":[3.448122004],"iteration":742,"passed_time":0.9351591683,"remaining_time":0.3234668994},
{"learn":[3.445646714],"iteration":743,"passed_time":0.936057418,"remaining_time":0.3220842729},
{"learn":[3.44411263],"iteration":744,"passed_time":0.9370379498,"remaining_time":0.3207311103},
{"learn":[3.443264164],"iteration":745,"passed_time":0.9380259124,"remaining_time":0.3193814769},
{"learn":[3.439521363],"iteration":746,"passed_time":0.9392792122,"remaining_time":0.3181226783},
{"learn":[3.436809225],"iteration":747,"passed_time":0.940363044,"remaining_time":0.3168068009},
{"learn":[3.435509465],"iteration":748,"passed_time":0.9414480347,"remaining_time":0.3154919315},
{"learn":[3.434450277],"iteration":749,"passed_time":0.9426274792,"remaining_time":0.3142091597},
{"learn":[3.431786753],"iteration":750,"passed_time":0.9436368498,"remaining_time":0.3128702738},
{"learn":[3.430150302],"iteration":751,"passed_time":0.9446598074,"remaining_time":0.311536745},
{"learn":[3.42696281],"iteration":752,"passed_time":0.9456671784,"remaining_time":0.3101989284},
{"learn":[3.426870334],"iteration":753,"passed_time":0.9466954531,"remaining_time":0.3088688083},
{"learn":[3.425200309],"iteration":754,"passed_time":0.947694615,"remaining_time":0.3075300406},
{"learn":[3.423383783],"iteration":755,"passed_time":0.9487112202,"remaining_time":0.3061978012},
{"learn":[3.422752979],"iteration":756,"passed_time":0.9495952973,"remaining_time":0.3048238537},
{"learn":[3.420845924],"iteration":757,"passed_time":0.950529693,"remaining_time":0.3034672635},
{"learn":[3.418917862],"iteration":758,"passed_time":0.9514845073,"remaining_time":0.3021182691},
{"learn":[3.417095735],"iteration":759,"passed_time":0.9525599165,"remaining_time":0.3008083947},
{"learn":[3.414391848],"iteration":760,"passed_time":0.9537253813,"remaining_time":0.2995274194},
{"learn":[3.41426711],"iteration":761,"passed_time":0.9545530973,"remaining_time":0.2981412561},
{"learn":[3.411976013],"iteration":762,"passed_time":0.9554778675,"remaining_time":0.2967867033},
{"learn":[3.408614844],"iteration":763,"passed_time":0.9563950722,"remaining_time":0.2954309385},
{"learn":[3.407906721],"iteration":764,"passed_time":0.9573392438,"remaining_time":0.2940846043},
{"learn":[3.407494015],"iteration":765,"passed_time":0.9584837593,"remaining_time":0.2928005218},
{"learn":[3.406287128],"iteration":766,"passed_time":0.9599721108,"remaining_time":0.291621254},
{"learn":[3.404600442],"iteration":767,"passed_time":0.9610128219,"remaining_time":0.2903059566},
{"learn":[3.404012662],"iteration":768,"passed_time":0.9623622492,"remaining_time":0.2890841087},
{"learn":[3.400398762],"iteration":769,"passed_time":0.9635448562,"remaining_time":0.2878120999},
{"learn":[3.399737714],"iteration":770,"passed_time":0.9644123051,"remaining_time":0.2864467158},
{"learn":[3.399185251],"iteration":771,"passed_time":0.9656506075,"remaining_time":0.2851921483},
{"learn":[3.397245411],"iteration":772,"passed_time":0.9667130552,"remaining_time":0.2838859813},
{"learn":[3.396229831],"iteration":773,"passed_time":0.9676539665,"remaining_time":0.2825449566},
{"learn":[3.394002836],"iteration":774,"passed_time":0.9686318352,"remaining_time":0.2812156941},
{"learn":[3.389617243],"iteration":775,"passed_time":0.9696406827,"remaining_time":0.2798962795},
{"learn":[3.385426488],"iteration":776,"passed_time":0.9706671072,"remaining_time":0.278582709},
{"learn":[3.385072258],"iteration":777,"passed_time":0.9715799367,"remaining_time":0.2772374626},
{"learn":[3.383842366],"iteration":778,"passed_time":0.9725440955,"remaining_time":0.2759078885},
{"learn":[3.380110746],"iteration":779,"passed_time":0.9735099241,"remaining_time":0.2745797222},
{"learn":[3.378595218],"iteration":780,"passed_time":0.9746064478,"remaining_time":0.273289132},
{"learn":[3.377371219],"iteration":781,"passed_time":0.97566615,"remaining_time":0.2719887733},
{"learn":[3.375814782],"iteration":782,"passed_time":0.9766774505,"remaining_time":0.2706756153},
{"learn":[3.374195887],"iteration":783,"passed_time":0.9778452075,"remaining_time":0.2694063327},
{"learn":[3.373704309],"iteration":784,"passed_time":0.978881537,"remaining_time":0.2681013127},
{"learn":[3.372971757],"iteration":785,"passed_time":0.9800494531,"remaining_time":0.2668328028},
{"learn":[3.371565136],"iteration":786,"passed_time":0.9814555078,"remaining_time":0.2656290002},
{"learn":[3.3700309],"iteration":787,"passed_time":0.9830819495,"remaining_time":0.2644839763},
{"learn":[3.368186663],"iteration":788,"passed_time":0.9841646254,"remaining_time":0.2631923143},
{"learn":[3.366710398],"iteration":789,"passed_time":0.9854355095,"remaining_time":0.2619512114},
{"learn":[3.364598042],"iteration":790,"passed_time":0.9864478265,"remaining_time":0.260641714},
{"learn":[3.36348442],"iteration":791,"passed_time":0.9876044731,"remaining_time":0.2593708717},
{"learn":[3.362001759],"iteration":792,"passed_time":0.9890840105,"remaining_time":0.258184603},
{"learn":[3.361580401],"iteration":793,"passed_time":0.9904829487,"remaining_time":0.2569766844},
{"learn":[3.359543675],"iteration":794,"passed_time":0.9916417294,"remaining_time":0.2557063579},
{"learn":[3.35766119],"iteration":795,"passed_time":0.9926360467,"remaining_time":0.2543941627},
{"learn":[3.354592969],"iteration":796,"passed_time":0.9936153406,"remaining_time":0.2530789387},
{"learn":[3.350985986],"iteration":797,"passed_time":0.9948102807,"remaining_time":0.2518191437},
{"learn":[3.349589624],"iteration":798,"passed_time":0.995835756,"remaining_time":0.2505168798},
{"learn":[3.349110856],"iteration":799,"passed_time":0.9968112564,"remaining_time":0.2492028141},
{"learn":[3.345315441],"iteration":800,"passed_time":0.9978040923,"remaining_time":0.2478939006},
{"learn":[3.34397474],"iteration":801,"passed_time":0.9988387781,"remaining_time":0.2465961073},
{"learn":[3.343800902],"iteration":802,"passed_time":0.9997654775,"remaining_time":0.2452724771},
{"learn":[3.342329465],"iteration":803,"passed_time":1.000566243,"remaining_time":0.2439191338},
{"learn":[3.34220347],"iteration":804,"passed_time":1.001557637,"remaining_time":0.2426133407},
{"learn":[3.341279219],"iteration":805,"passed_time":1.002392764,"remaining_time":0.241270715},
{"learn":[3.337329521],"iteration":806,"passed_time":1.003268182,"remaining_time":0.2399389827},
{"learn":[3.336708453],"iteration":807,"passed_time":1.004414835,"remaining_time":0.238672832},
{"learn":[3.333252703],"iteration":808,"passed_time":1.00556923,"remaining_time":0.2374088045},
{"learn":[3.332186769],"iteration":809,"passed_time":1.006692195,"remaining_time":0.2361376754},
{"learn":[3.330594851],"iteration":810,"passed_time":1.007719893,"remaining_time":0.23484471},
{"learn":[3.327867442],"iteration":811,"passed_time":1.008773329,"remaining_time":0.2335583568},
{"learn":[3.327563111],"iteration":812,"passed_time":1.009665712,"remaining_time":0.2322355329},
{"learn":[3.326308994],"iteration":813,"passed_time":1.010699594,"remaining_time":0.2309460989},
{"learn":[3.326249879],"iteration":814,"passed_time":1.011564856,"remaining_time":0.2296190164},
{"learn":[3.322336238],"iteration":815,"passed_time":1.012719991,"remaining_time":0.2283584294},
{"learn":[3.320491154],"iteration":816,"passed_time":1.013810628,"remaining_time":0.2270836536},
{"learn":[3.320434271],"iteration":817,"passed_time":1.015052049,"remaining_time":0.2258428763},
{"learn":[3.319609638],"iteration":818,"passed_time":1.015919328,"remaining_time":0.224519412},
{"learn":[3.316182682],"iteration":819,"passed_time":1.016959699,"remaining_time":0.2232350558},
{"learn":[3.313126612],"iteration":820,"passed_time":1.017962678,"remaining_time":0.2219431418},
{"learn":[3.311222803],"iteration":821,"passed_time":1.018964303,"remaining_time":0.2206516373},
{"learn":[3.309627335],"iteration":822,"passed_time":1.020011874,"remaining_time":0.2193707189},
{"learn":[3.307974895],"iteration":823,"passed_time":1.021240882,"remaining_time":0.2181291205},
{"learn":[3.307321505],"iteration":824,"passed_time":1.02260621,"remaining_time":0.2169164687},
{"learn":[3.306759087],"iteration":825,"passed_time":1.023451345,"remaining_time":0.2155938669},
{"learn":[3.30484037],"iteration":826,"passed_time":1.024738466,"remaining_time":0.2143648787},
{"learn":[3.30201994],"iteration":827,"passed_time":1.025718916,"remaining_time":0.2130720455},
{"learn":[3.299302297],"iteration":828,"passed_time":1.02735487,"remaining_time":0.2119151782},
{"learn":[3.298132671],"iteration":829,"passed_time":1.028442616,"remaining_time":0.2106448731},
{"learn":[3.296976183],"iteration":830,"passed_time":1.02950778,"remaining_time":0.2093704149},
{"learn":[3.293144745],"iteration":831,"passed_time":1.030639586,"remaining_time":0.2081099163},
{"learn":[3.290284404],"iteration":832,"passed_time":1.031696288,"remaining_time":0.20683467},
{"learn":[3.288285745],"iteration":833,"passed_time":1.032882643,"remaining_time":0.2055857539},
{"learn":[3.286662667],"iteration":834,"passed_time":1.034089016,"remaining_time":0.2043409433},
{"learn":[3.285692682],"iteration":835,"passed_time":1.035481938,"remaining_time":0.2031328204},
{"learn":[3.284565611],"iteration":836,"passed_time":1.036864541,"remaining_time":0.2019222464},
{"learn":[3.283897383],"iteration":837,"passed_time":1.038166241,"remaining_time":0.2006956217},
{"learn":[3.280712855],"iteration":838,"passed_time":1.039262141,"remaining_time":0.1994293262},
{"learn":[3.280468341],"iteration":839,"passed_time":1.040259329,"remaining_time":0.198144634},
{"learn":[3.277814895],"iteration":840,"passed_time":1.04114422,"remaining_time":0.1968393947},
{"learn":[3.276316385],"iteration":841,"passed_time":1.042227801,"remaining_time":0.1955724377},
{"learn":[3.27557063],"iteration":842,"passed_time":1.043330177,"remaining_time":0.1943094161},
{"learn":[3.27499628],"iteration":843,"passed_time":1.044301462,"remaining_time":0.1930225451},
{"learn":[3.273569958],"iteration":844,"passed_time":1.045344383,"remaining_time":0.1917495614},
{"learn":[3.269665595],"iteration":845,"passed_time":1.046278076,"remaining_time":0.1904572384},
{"learn":[3.267984685],"iteration":846,"passed_time":1.047156808,"remaining_time":0.1891558342},
{"learn":[3.267702508],"iteration":847,"passed_time":1.048080636,"remaining_time":0.1878635103},
{"learn":[3.266671924],"iteration":848,"passed_time":1.04907572,"remaining_time":0.1865847276},
{"learn":[3.265359825],"iteration":849,"passed_time":1.049934793,"remaining_time":0.1852826106},
{"learn":[3.2618983],"iteration":850,"passed_time":1.051095306,"remaining_time":0.1840343132},
{"learn":[3.260456253],"iteration":851,"passed_time":1.052041704,"remaining_time":0.1827490283},
{"learn":[3.258389147],"iteration":852,"passed_time":1.053161801,"remaining_time":0.1814944721},
{"learn":[3.258108469],"iteration":853,"passed_time":1.054324681,"remaining_time":0.1802475449},
{"learn":[3.256424936],"iteration":854,"passed_time":1.055213798,"remaining_time":0.1789543869},
{"learn":[3.254817983],"iteration":855,"passed_time":1.056066201,"remaining_time":0.1776559965},
{"learn":[3.253898449],"iteration":856,"passed_time":1.056998372,"remaining_time":0.176371957},
{"learn":[3.253023652],"iteration":857,"passed_time":1.057963697,"remaining_time":0.175094225},
{"learn":[3.252845542],"iteration":858,"passed_time":1.059525139,"remaining_time":0.1739150694},
{"learn":[3.252316026],"iteration":859,"passed_time":1.060691464,"remaining_time":0.1726707035},
{"learn":[3.24975301],"iteration":860,"passed_time":1.061872438,"remaining_time":0.1714288837},
{"learn":[3.249151075],"iteration":861,"passed_time":1.06293662,"remaining_time":0.1701685077},
{"learn":[3.246257135],"iteration":862,"passed_time":1.064141367,"remaining_time":0.1689309007},
{"learn":[3.243826471],"iteration":863,"passed_time":1.065118375,"remaining_time":0.1676575221},
{"learn":[3.243190653],"iteration":864,"passed_time":1.066053009,"remaining_time":0.1663782152},
{"learn":[3.24008797],"iteration":865,"passed_time":1.066956824,"remaining_time":0.1650949358},
{"learn":[3.240036811],"iteration":866,"passed_time":1.068462545,"remaining_time":0.1639048657},
{"learn":[3.238676314],"iteration":867,"passed_time":1.069372493,"remaining_time":0.1626234667},
{"learn":[3.237848782],"iteration":868,"passed_time":1.070221525,"remaining_time":0.1613337397},
{"learn":[3.236405498],"iteration":869,"passed_time":1.07106615,"remaining_time":0.1600443672},
{"learn":[3.233378068],"iteration":870,"passed_time":1.07209827,"remaining_time":0.1587837852},
{"learn":[3.233169169],"iteration":871,"passed_time":1.073151129,"remaining_time":0.1575267712},
{"learn":[3.232434885],"iteration":872,"passed_time":1.074091524,"remaining_time":0.1562538643},
{"learn":[3.229978115],"iteration":873,"passed_time":1.075134851,"remaining_time":0.1549965575},
{"learn":[3.229648848],"iteration":874,"passed_time":1.076494345,"remaining_time":0.1537849064},
{"learn":[3.227208761],"iteration":875,"passed_time":1.077737937,"remaining_time":0.1525565116},
{"learn":[3.226258869],"iteration":876,"passed_time":1.078729807,"remaining_time":0.1512927779},
{"learn":[3.225331995],"iteration":877,"passed_time":1.079656116,"remaining_time":0.1500205537},
{"learn":[3.221968268],"iteration":878,"passed_time":1.080607184,"remaining_time":0.1487525248},
{"learn":[3.221166317],"iteration":879,"passed_time":1.081775804,"remaining_time":0.1475148824},
{"learn":[3.220047503],"iteration":880,"passed_time":1.082804755,"remaining_time":0.146258531},
{"learn":[3.21982781],"iteration":881,"passed_time":1.083862612,"remaining_time":0.1450065626},
{"learn":[3.216693405],"iteration":882,"passed_time":1.084808746,"remaining_time":0.1437402302},
{"learn":[3.214798761],"iteration":883,"passed_time":1.085774697,"remaining_time":0.1424772227},
{"learn":[3.214395085],"iteration":884,"passed_time":1.086813879,"remaining_time":0.1412244024},
{"learn":[3.213470696],"iteration":885,"passed_time":1.087933208,"remaining_time":0.1399823766},
{"learn":[3.211595017],"iteration":886,"passed_time":1.08897718,"remaining_time":0.1387310274},
{"learn":[3.210965255],"iteration":887,"passed_time":1.089939158,"remaining_time":0.1374698037},
{"learn":[3.209413583],"iteration":888,"passed_time":1.091156231,"remaining_time":0.1362411042},
{"learn":[3.208331683],"iteration":889,"passed_time":1.092054698,"remaining_time":0.1349730526},
{"learn":[3.207110711],"iteration":890,"passed_time":1.092940314,"remaining_time":0.1337042583},
{"learn":[3.204519413],"iteration":891,"passed_time":1.093862545,"remaining_time":0.1324407566},
{"learn":[3.201421296],"iteration":892,"passed_time":1.094721594,"remaining_time":0.1311704486},
{"learn":[3.200691259],"iteration":893,"passed_time":1.095613375,"remaining_time":0.1299049416},
{"learn":[3.200485067],"iteration":894,"passed_time":1.096532158,"remaining_time":0.1286434375},
{"learn":[3.197467568],"iteration":895,"passed_time":1.097449681,"remaining_time":0.1273825522},
{"learn":[3.195838544],"iteration":896,"passed_time":1.09840839,"remaining_time":0.1261271619},
{"learn":[3.195671746],"iteration":897,"passed_time":1.099254524,"remaining_time":0.1248596453},
{"learn":[3.194213094],"iteration":898,"passed_time":1.100245601,"remaining_time":0.1236093501},
{"learn":[3.192884691],"iteration":899,"passed_time":1.10112341,"remaining_time":0.1223470455},
{"learn":[3.188364239],"iteration":900,"passed_time":1.101925586,"remaining_time":0.1210772842},
{"learn":[3.185219478],"iteration":901,"passed_time":1.102879245,"remaining_time":0.1198250178},
{"learn":[3.184120387],"iteration":902,"passed_time":1.103935331,"remaining_time":0.1185844154},
{"learn":[3.183725321],"iteration":903,"passed_time":1.105397673,"remaining_time":0.1173873636},
{"learn":[3.181264554],"iteration":904,"passed_time":1.106344293,"remaining_time":0.1161355887},
{"learn":[3.180741589],"iteration":905,"passed_time":1.107581644,"remaining_time":0.1149146518},
{"learn":[3.179782639],"iteration":906,"passed_time":1.10843933,"remaining_time":0.1136547493},
{"learn":[3.176377564],"iteration":907,"passed_time":1.10933817,"remaining_time":0.1123999027},
{"learn":[3.174078182],"iteration":908,"passed_time":1.110211419,"remaining_time":0.1111432773},
{"learn":[3.171242379],"iteration":909,"passed_time":1.111165036,"remaining_time":0.1098954431},
{"learn":[3.170421012],"iteration":910,"passed_time":1.112062975,"remaining_time":0.1086428154},
{"learn":[3.170087224],"iteration":911,"passed_time":1.113041845,"remaining_time":0.1073987745},
{"learn":[3.167303059],"iteration":912,"passed_time":1.113972963,"remaining_time":0.1061507643},
{"learn":[3.16705966],"iteration":913,"passed_time":1.1148729,"remaining_time":0.1049005136},
{"learn":[3.165667683],"iteration":914,"passed_time":1.115836565,"remaining_time":0.1036569487},
{"learn":[3.164689733],"iteration":915,"passed_time":1.116775817,"remaining_time":0.1024117561},
{"learn":[3.163311455],"iteration":916,"passed_time":1.117685298,"remaining_time":0.1011645363},
{"learn":[3.159425016],"iteration":917,"passed_time":1.118595717,"remaining_time":0.09991813594},
{"learn":[3.159327058],"iteration":918,"passed_time":1.119569442,"remaining_time":0.09867804654},
{"learn":[3.15819426],"iteration":919,"passed_time":1.120463296,"remaining_time":0.09743159092},
{"learn":[3.157086603],"iteration":920,"passed_time":1.121320627,"remaining_time":0.0961827682},
{"learn":[3.153354154],"iteration":921,"passed_time":1.122109855,"remaining_time":0.09492903326},
{"learn":[3.153261317],"iteration":922,"passed_time":1.122909554,"remaining_time":0.09367717842},
{"learn":[3.153168454],"iteration":923,"passed_time":1.123671747,"remaining_time":0.09242321729},
{"learn":[3.152080399],"iteration":924,"passed_time":1.124491539,"remaining_time":0.09117498964},
{"learn":[3.151635144],"iteration":925,"passed_time":1.125348802,"remaining_time":0.08993068179},
{"learn":[3.147762655],"iteration":926,"passed_time":1.126231553,"remaining_time":0.08868921614},
{"learn":[3.147172317],"iteration":927,"passed_time":1.12720997,"remaining_time":0.08745594593},
{"learn":[3.146254125],"iteration":928,"passed_time":1.12867482,"remaining_time":0.0862604007},
{"learn":[3.144869828],"iteration":929,"passed_time":1.129482628,"remaining_time":0.08501482146},
{"learn":[3.143466218],"iteration":930,"passed_time":1.130466278,"remaining_time":0.08378321499},
{"learn":[3.141919643],"iteration":931,"passed_time":1.131271521,"remaining_time":0.08253912388},
{"learn":[3.141054135],"iteration":932,"passed_time":1.132084163,"remaining_time":0.08129650475},
{"learn":[3.139390417],"iteration":933,"passed_time":1.133094201,"remaining_time":0.08006875512},
{"learn":[3.139025283],"iteration":934,"passed_time":1.133994326,"remaining_time":0.07883383018},
{"learn":[3.137824183],"iteration":935,"passed_time":1.134934941,"remaining_time":0.07760238916},
{"learn":[3.135620453],"iteration":936,"passed_time":1.135987684,"remaining_time":0.07637910787},
{"learn":[3.13443178],"iteration":937,"passed_time":1.136920946,"remaining_time":0.07514829281},
{"learn":[3.132765713],"iteration":938,"passed_time":1.137939805,"remaining_time":0.07392367213},
{"learn":[3.131434124],"iteration":939,"passed_time":1.138931151,"remaining_time":0.07269773304},
{"learn":[3.128384262],"iteration":940,"passed_time":1.139734275,"remaining_time":0.07146049123},
{"learn":[3.128120455],"iteration":941,"passed_time":1.140578387,"remaining_time":0.07022669476},
{"learn":[3.126314615],"iteration":942,"passed_time":1.141398142,"remaining_time":0.06899225248},
{"learn":[3.125409666],"iteration":943,"passed_time":1.142409258,"remaining_time":0.0677700407},
{"learn":[3.123072589],"iteration":944,"passed_time":1.143632184,"remaining_time":0.06656060332},
{"learn":[3.122921099],"iteration":945,"passed_time":1.144532646,"remaining_time":0.06533273033},
{"learn":[3.122182662],"iteration":946,"passed_time":1.145432309,"remaining_time":0.06410550407},
{"learn":[3.120040951],"iteration":947,"passed_time":1.146281949,"remaining_time":0.06287622504},
{"learn":[3.118767799],"iteration":948,"passed_time":1.147176642,"remaining_time":0.06165016726},
{"learn":[3.118203218],"iteration":949,"passed_time":1.148030327,"remaining_time":0.0604226488},
{"learn":[3.116343362],"iteration":950,"passed_time":1.148914179,"remaining_time":0.05919747087},
{"learn":[3.11480829],"iteration":951,"passed_time":1.14981711,"remaining_time":0.05797397193},
{"learn":[3.112607903],"iteration":952,"passed_time":1.150800851,"remaining_time":0.05675513118},
{"learn":[3.111661241],"iteration":953,"passed_time":1.151926401,"remaining_time":0.055543621},
{"learn":[3.110249676],"iteration":954,"passed_time":1.152920206,"remaining_time":0.05432608299},
{"learn":[3.107333579],"iteration":955,"passed_time":1.153825583,"remaining_time":0.05310494314},
{"learn":[3.107149851],"iteration":956,"passed_time":1.154721343,"remaining_time":0.0518840311},
{"learn":[3.106867336],"iteration":957,"passed_time":1.155582198,"remaining_time":0.05066226754},
{"learn":[3.10364681],"iteration":958,"passed_time":1.156471698,"remaining_time":0.04944248136},
{"learn":[3.102703811],"iteration":959,"passed_time":1.157438486,"remaining_time":0.04822660356},
{"learn":[3.101469264],"iteration":960,"passed_time":1.158559319,"remaining_time":0.04701749578},
{"learn":[3.09863569],"iteration":961,"passed_time":1.159539459,"remaining_time":0.04580301395},
{"learn":[3.09645939],"iteration":962,"passed_time":1.160357291,"remaining_time":0.04458278273},
{"learn":[3.096240186],"iteration":963,"passed_time":1.16128944,"remaining_time":0.04336765542},
{"learn":[3.094838828],"iteration":964,"passed_time":1.162169828,"remaining_time":0.04215123728},
{"learn":[3.094176802],"iteration":965,"passed_time":1.16307899,"remaining_time":0.04093652759},
{"learn":[3.093182279],"iteration":966,"passed_time":1.164086825,"remaining_time":0.03972581719},
{"learn":[3.090150687],"iteration":967,"passed_time":1.165000525,"remaining_time":0.03851241406},
{"learn":[3.088612829],"iteration":968,"passed_time":1.165978977,"remaining_time":0.03730170101},
{"learn":[3.087153684],"iteration":969,"passed_time":1.166910854,"remaining_time":0.03609002641},
{"learn":[3.085866843],"iteration":970,"passed_time":1.167800206,"remaining_time":0.03487765805},
{"learn":[3.082669094],"iteration":971,"passed_time":1.168694072,"remaining_time":0.03366608439},
{"learn":[3.081047548],"iteration":972,"passed_time":1.169543431,"remaining_time":0.0324539287},
{"learn":[3.079684322],"iteration":973,"passed_time":1.170397653,"remaining_time":0.03124264781},
{"learn":[3.07613431],"iteration":974,"passed_time":1.171304899,"remaining_time":0.03003345895},
{"learn":[3.074005935],"iteration":975,"passed_time":1.172282922,"remaining_time":0.02882662924},
{"learn":[3.072988853],"iteration":976,"passed_time":1.173257992,"remaining_time":0.02762019839},
{"learn":[3.072344268],"iteration":977,"passed_time":1.174144431,"remaining_time":0.02641224692},
{"learn":[3.070654438],"iteration":978,"passed_time":1.175087162,"remaining_time":0.02520615975},
{"learn":[3.069724506],"iteration":979,"passed_time":1.175936115,"remaining_time":0.02399869623},
{"learn":[3.067763166],"iteration":980,"passed_time":1.176848252,"remaining_time":0.02279318735},
{"learn":[3.066737893],"iteration":981,"passed_time":1.177717821,"remaining_time":0.0215874957},
{"learn":[3.065248174],"iteration":982,"passed_time":1.178604523,"remaining_time":0.02038278422},
{"learn":[3.063186837],"iteration":983,"passed_time":1.179471462,"remaining_time":0.01917839776},
{"learn":[3.062880371],"iteration":984,"passed_time":1.180385911,"remaining_time":0.01797541997},
{"learn":[3.061288645],"iteration":985,"passed_time":1.18159148,"remaining_time":0.01677716097},
{"learn":[3.059970575],"iteration":986,"passed_time":1.182741603,"remaining_time":0.01557815688},
{"learn":[3.059576341],"iteration":987,"passed_time":1.183602021,"remaining_time":0.01437573304},
{"learn":[3.058175919],"iteration":988,"passed_time":1.184479558,"remaining_time":0.01317419124},
{"learn":[3.056830702],"iteration":989,"passed_time":1.185354392,"remaining_time":0.01197327669},
{"learn":[3.056336579],"iteration":990,"passed_time":1.186109586,"remaining_time":0.01077193368},
{"learn":[3.055810414],"iteration":991,"passed_time":1.186901972,"remaining_time":0.009571790093},
{"learn":[3.055476518],"iteration":992,"passed_time":1.187646858,"remaining_time":0.008372132934},
{"learn":[3.053331734],"iteration":993,"passed_time":1.188637146,"remaining_time":0.007174872107},
{"learn":[3.050890374],"iteration":994,"passed_time":1.189533952,"remaining_time":0.005977557547},
{"learn":[3.04972623],"iteration":995,"passed_time":1.190456161,"remaining_time":0.004780948437},
{"learn":[3.047217327],"iteration":996,"passed_time":1.191578099,"remaining_time":0.003585490768},
{"learn":[3.047155483],"iteration":997,"passed_time":1.192552433,"remaining_time":0.002389884636},
{"learn":[3.04430671],"iteration":998,"passed_time":1.193413348,"remaining_time":0.001194607956},
{"learn":[3.042664195],"iteration":999,"passed_time":1.19428159,"remaining_time":0}
]}